<mujoco>
  <visual>
    <headlight diffuse="0.6 0.6 0.6" ambient="0.1 0.1 0.1" specular="0 0 0"/>
    <rgba haze="0.15 0.25 0.35 1"/>
    <global azimuth="120" elevation="-20"/>
  </visual>

  <asset>
    <texture type="skybox" builtin="gradient" rgb1="0.3 0.5 0.7" rgb2="0 0 0" width="512" height="3072"/>
    <texture type="2d" name="groundplane" builtin="checker" mark="edge" rgb1="0.2 0.3 0.4" rgb2="0.1 0.2 0.3"
      markrgb="0.8 0.8 0.8" width="300" height="300"/>
    <material name="groundplane" texture="groundplane" texuniform="true" texrepeat="5 5" reflectance="0.2"/>
  </asset>

  <worldbody>
    <light pos="0 0 1.5" dir="0 0 -1" directional="true"/>
    <geom name="floor" size="0 0 0.05" type="plane" material="groundplane"/>
 
      
    <body pos="1.4389599889981402e-16 2.35 1.0" euler="0 0 180.0" >
         <geom type="box" size="0.1 0.30000000000000004  1.0" rgba="1.0 0.0 0.0 1"/>
         <freejoint/>
        </body>
    <body pos="-1.022829582213672 2.2220122964020788 1.0" euler="0 0 204.71740953034254" >
         <geom type="box" size="0.1 0.30000000000000004  1.0" rgba="1.0 0.015000000000000013 0.0 1"/>
         <freejoint/>
        </body>
    <body pos="-2.1468753337200184 1.4132491889578191 1.0" euler="0 0 236.64381325441045" >
         <geom type="box" size="0.1 0.30000000000000004  1.0" rgba="1.0 0.030000000000000027 0.0 1"/>
         <freejoint/>
        </body>
    <body pos="-2.685471933434647 0.1345880456307411 1.0" euler="0 0 267.130902630213" >
         <geom type="box" size="0.1 0.30000000000000004  1.0" rgba="1.0 0.04500000000000004 0.0 1"/>
         <freejoint/>
        </body>
    <body pos="-2.5116184480545165 -1.2430747666013353 1.0" euler="0 0 296.3321784166742" >
         <geom type="box" size="0.1 0.30000000000000004  1.0" rgba="1.0 0.06000000000000005 0.0 1"/>
         <freejoint/>
        </body>
    <body pos="-1.6945075772089044 -2.367703044150444 1.0" euler="0 0 324.409621366919" >
         <geom type="box" size="0.1 0.30000000000000004  1.0" rgba="1.0 0.07499999999999996 0.0 1"/>
         <freejoint/>
        </body>
    <body pos="-0.4466632108807512 -2.98364088912707 1.0" euler="0 0 351.4858170496435" >
         <geom type="box" size="0.1 0.30000000000000004  1.0" rgba="1.0 0.08999999999999997 0.0 1"/>
         <freejoint/>
        </body>
    <body pos="0.9460195156832572 -2.9717264800983356 1.0" euler="0 0 377.6583556874466" >
         <geom type="box" size="0.1 0.30000000000000004  1.0" rgba="1.0 0.10499999999999998 0.0 1"/>
         <freejoint/>
        </body>
    <body pos="2.1946896900557684 -2.3524817706889336 1.0" euler="0 0 403.0125680185668" >
         <geom type="box" size="0.1 0.30000000000000004  1.0" rgba="1.0 0.12 0.0 1"/>
         <freejoint/>
        </body>
    <body pos="3.0635174588375698 -1.2612280583451505 1.0" euler="0 0 427.62338803061596" >
         <geom type="box" size="0.1 0.30000000000000004  1.0" rgba="1.0 0.135 0.0 1"/>
         <freejoint/>
        </body>
    <body pos="3.404771018798713 0.0918568709849327 1.0" euler="0 0 451.54540045259847" >
         <geom type="box" size="0.1 0.30000000000000004  1.0" rgba="1.0 0.15000000000000002 0.0 1"/>
         <freejoint/>
        </body>
    <body pos="3.173318906360834 1.468332960723826 1.0" euler="0 0 474.8305501384257" >
         <geom type="box" size="0.1 0.30000000000000004  1.0" rgba="1.0 0.16500000000000004 0.0 1"/>
         <freejoint/>
        </body>
    <body pos="2.419839618667701 2.644970258250555 1.0" euler="0 0 497.54512026191867" >
         <geom type="box" size="0.1 0.30000000000000004  1.0" rgba="1.0 0.17999999999999994 0.0 1"/>
         <freejoint/>
        </body>
    <body pos="1.2733162852660582 3.4431761753829058 1.0" euler="0 0 519.7051709612304" >
         <geom type="box" size="0.1 0.30000000000000004  1.0" rgba="1.0 0.19500000000000006 0.0 1"/>
         <freejoint/>
        </body>
    <body pos="-0.09000271430206543 3.7542619893320097 1.0" euler="0 0 541.3733160114086" >
         <geom type="box" size="0.1 0.30000000000000004  1.0" rgba="1.0 0.20999999999999996 0.0 1"/>
         <freejoint/>
        </body>
    <body pos="-1.4721122297971996 3.5441460335705934 1.0" euler="0 0 562.5562607304066" >
         <geom type="box" size="0.1 0.30000000000000004  1.0" rgba="1.0 0.22499999999999998 0.0 1"/>
         <freejoint/>
        </body>
    <body pos="-2.6877552945930114 2.851316509104424 1.0" euler="0 0 583.3086254732577" >
         <geom type="box" size="0.1 0.30000000000000004  1.0" rgba="1.0 0.24 0.0 1"/>
         <freejoint/>
        </body>
    <body pos="-3.5818592243112364 1.7748862586862295 1.0" euler="0 0 603.6406213019918" >
         <geom type="box" size="0.1 0.30000000000000004  1.0" rgba="1.0 0.255 0.0 1"/>
         <freejoint/>
        </body>
    <body pos="-4.049443140451536 0.4558638569252205 1.0" euler="0 0 623.5770006309575" >
         <geom type="box" size="0.1 0.30000000000000004  1.0" rgba="1.0 0.27 0.0 1"/>
         <freejoint/>
        </body>
    <body pos="-4.042308777617758 -0.9442659731429738 1.0" euler="0 0 643.1482781343453" >
         <geom type="box" size="0.1 0.30000000000000004  1.0" rgba="1.0 0.28500000000000003 0.0 1"/>
         <freejoint/>
        </body>
    <body pos="-3.5691405203615845 -2.2626079650220987 1.0" euler="0 0 662.3720965831905" >
         <geom type="box" size="0.1 0.30000000000000004  1.0" rgba="1.0 0.30000000000000004 0.0 1"/>
         <freejoint/>
        </body>
    <body pos="-2.6901959143692844 -3.3537106563531482 1.0" euler="0 0 681.2649813138355" >
         <geom type="box" size="0.1 0.30000000000000004  1.0" rgba="1.0 0.31499999999999995 0.0 1"/>
         <freejoint/>
        </body>
    <body pos="-1.5069170377846322 -4.1036513084987005 1.0" euler="0 0 699.8360725150611" >
         <geom type="box" size="0.1 0.30000000000000004  1.0" rgba="1.0 0.33000000000000007 0.0 1"/>
         <freejoint/>
        </body>
    <body pos="-0.14671454474788528 -4.4402170917063355 1.0" euler="0 0 718.1075098798844" >
         <geom type="box" size="0.1 0.30000000000000004  1.0" rgba="1.0 0.345 0.0 1"/>
         <freejoint/>
        </body>
    <body pos="1.250954878884252 -4.3357307741942535 1.0" euler="0 0 736.0940285814786" >
         <geom type="box" size="0.1 0.30000000000000004  1.0" rgba="1.0 0.36 0.0 1"/>
         <freejoint/>
        </body>
    <body pos="2.549205563426153 -3.8067675604151443 1.0" euler="0 0 753.8082805624449" >
         <geom type="box" size="0.1 0.30000000000000004  1.0" rgba="1.0 0.375 0.0 1"/>
         <freejoint/>
        </body>
    <body pos="3.6265767751244584 -2.909368230434822 1.0" euler="0 0 771.2621802975323" >
         <geom type="box" size="0.1 0.30000000000000004  1.0" rgba="1.0 0.39 0.0 1"/>
         <freejoint/>
        </body>
    <body pos="4.387093964044367 -1.7310455300122192 1.0" euler="0 0 788.4669577024617" >
         <geom type="box" size="0.1 0.30000000000000004  1.0" rgba="1.0 0.405 0.0 1"/>
         <freejoint/>
        </body>
    <body pos="4.767057550429181 -0.3807677741223126 1.0" euler="0 0 805.4332065565949" >
         <geom type="box" size="0.1 0.30000000000000004  1.0" rgba="1.0 0.42000000000000004 0.0 1"/>
         <freejoint/>
        </body>
    <body pos="4.7383788243348866 1.0219516592624691 1.0" euler="0 0 822.1708618118773" >
         <geom type="box" size="0.1 0.30000000000000004  1.0" rgba="1.0 0.43499999999999994 0.0 1"/>
         <freejoint/>
        </body>
    <body pos="4.308878674383421 2.3572870464013223 1.0" euler="0 0 838.6820409297716" >
         <geom type="box" size="0.1 0.30000000000000004  1.0" rgba="1.0 0.44999999999999996 0.0 1"/>
         <freejoint/>
        </body>
    <body pos="3.5189207162067686 3.516691564299237 1.0" euler="0 0 854.9818464993764" >
         <geom type="box" size="0.1 0.30000000000000004  1.0" rgba="1.0 0.46499999999999997 0.0 1"/>
         <freejoint/>
        </body>
    <body pos="2.436177216773626 4.409278552152406 1.0" euler="0 0 871.0788437589476" >
         <geom type="box" size="0.1 0.30000000000000004  1.0" rgba="1.0 0.48 0.0 1"/>
         <freejoint/>
        </body>
    <body pos="1.1487442328153652 4.968296727237959 1.0" euler="0 0 886.9811416841094" >
         <geom type="box" size="0.1 0.30000000000000004  1.0" rgba="1.0 0.495 0.0 1"/>
         <freejoint/>
        </body>
    <body pos="-0.24277036451475975 5.154772470950802 1.0" euler="0 0 902.6964229454186" >
         <geom type="box" size="0.1 0.30000000000000004  1.0" rgba="1.0 0.51 0.0 1"/>
         <freejoint/>
        </body>
    <body pos="-1.6330268777326387 4.958916430173085 1.0" euler="0 0 918.227294667898" >
         <geom type="box" size="0.1 0.30000000000000004  1.0" rgba="1.0 0.525 0.0 1"/>
         <freejoint/>
        </body>
    <body pos="-2.920357012248162 4.399540501577272 1.0" euler="0 0 933.5756828743665" >
         <geom type="box" size="0.1 0.30000000000000004  1.0" rgba="1.0 0.54 0.0 1"/>
         <freejoint/>
        </body>
    <body pos="-4.014969336956969 3.5201515487223176 1.0" euler="0 0 948.757116003877" >
         <geom type="box" size="0.1 0.30000000000000004  1.0" rgba="1.0 0.5549999999999999 0.0 1"/>
         <freejoint/>
        </body>
    <body pos="-4.842503315785917 2.3851283067935487 1.0" euler="0 0 963.7778929331006" >
         <geom type="box" size="0.1 0.30000000000000004  1.0" rgba="1.0 0.5700000000000001 0.0 1"/>
         <freejoint/>
        </body>
    <body pos="-5.3487614423627345 1.0753685508627455 1.0" euler="0 0 978.6322318760224" >
         <geom type="box" size="0.1 0.30000000000000004  1.0" rgba="1.0 0.585 0.0 1"/>
         <freejoint/>
        </body>
    <body pos="-5.503638624112446 -0.32039711807293947 1.0" euler="0 0 993.3317424943936" >
         <geom type="box" size="0.1 0.30000000000000004  1.0" rgba="1.0 0.6000000000000001 0.0 1"/>
         <freejoint/>
        </body>
    <body pos="-5.300344491784645 -1.7106617739117196 1.0" euler="0 0 1007.8872459512345" >
         <geom type="box" size="0.1 0.30000000000000004  1.0" rgba="1.0 0.615 0.0 1"/>
         <freejoint/>
        </body>
    <body pos="-4.755578306468872 -3.005255813899309 1.0" euler="0 0 1022.2905647080354" >
         <geom type="box" size="0.1 0.30000000000000004  1.0" rgba="1.0 0.63 0.0 1"/>
         <freejoint/>
        </body>
    <body pos="-3.906704182541668 -4.1245490146422386 1.0" euler="0 0 1036.5537462733782" >
         <geom type="box" size="0.1 0.30000000000000004  1.0" rgba="1.0 0.645 0.0 1"/>
         <freejoint/>
        </body>
    <body pos="-2.8083009722626637 -5.001516228334386 1.0" euler="0 0 1050.686228327099" >
         <geom type="box" size="0.1 0.30000000000000004  1.0" rgba="1.0 0.66 0.0 1"/>
         <freejoint/>
        </body>
    <body pos="-1.5304618406693289 -5.58447912539515 1.0" euler="0 0 1064.6740278723978" >
         <geom type="box" size="0.1 0.30000000000000004  1.0" rgba="1.0 0.675 0.0 1"/>
         <freejoint/>
        </body>
    <body pos="-0.14879901737161183 -5.842431824049535 1.0" euler="0 0 1078.5410676089216" >
         <geom type="box" size="0.1 0.30000000000000004  1.0" rgba="1.0 0.6900000000000001 0.0 1"/>
         <freejoint/>
        </body>
    <body pos="1.2540349022617636 -5.762877458542166 1.0" euler="0 0 1092.276502071114" >
         <geom type="box" size="0.1 0.30000000000000004  1.0" rgba="1.0 0.7050000000000001 0.0 1"/>
         <freejoint/>
        </body>
    <body pos="2.598513844100924 -5.353358295275438 1.0" euler="0 0 1105.8918819380674" >
         <geom type="box" size="0.1 0.30000000000000004  1.0" rgba="1.0 0.72 0.0 1"/>
         <freejoint/>
        </body>
    <body pos="3.809397392127354 -4.63967581413087 1.0" euler="0 0 1119.3876444857872" >
         <geom type="box" size="0.1 0.30000000000000004  1.0" rgba="1.0 0.735 0.0 1"/>
         <freejoint/>
        </body>
    <body pos="4.820933116960452 -3.6638824464804394 1.0" euler="0 0 1132.7653673312318" >
         <geom type="box" size="0.1 0.30000000000000004  1.0" rgba="1.0 0.75 0.0 1"/>
         <freejoint/>
        </body>
    <body pos="5.580225013441679 -2.4807244772872825 1.0" euler="0 0 1146.0321570218102" >
         <geom type="box" size="0.1 0.30000000000000004  1.0" rgba="1.0 0.765 0.0 1"/>
         <freejoint/>
        </body>
    <body pos="6.048571461915314 -1.155439808345262 1.0" euler="0 0 1159.1852570311862" >
         <geom type="box" size="0.1 0.30000000000000004  1.0" rgba="1.0 0.78 0.0 1"/>
         <freejoint/>
        </body>
    <body pos="6.203969229849966 0.24192338947903633 1.0" euler="0 0 1172.2331138782456" >
         <geom type="box" size="0.1 0.30000000000000004  1.0" rgba="1.0 0.795 0.0 1"/>
         <freejoint/>
        </body>
    <body pos="6.040798473924799 1.6382756762434219 1.0" euler="0 0 1185.173737349101" >
         <geom type="box" size="0.1 0.30000000000000004  1.0" rgba="1.0 0.81 0.0 1"/>
         <freejoint/>
        </body>
    <body pos="5.569834500247798 2.963041691525283 1.0" euler="0 0 1198.012093371943" >
         <geom type="box" size="0.1 0.30000000000000004  1.0" rgba="1.0 0.8250000000000001 0.0 1"/>
         <freejoint/>
        </body>
    <body pos="4.816846688961691 4.150690870158437 1.0" euler="0 0 1210.7515716127468" >
         <geom type="box" size="0.1 0.30000000000000004  1.0" rgba="1.0 0.8400000000000001 0.0 1"/>
         <freejoint/>
        </body>
    <body pos="3.8213463010007307 5.143439623340649 1.0" euler="0 0 1223.389297161536" >
         <geom type="box" size="0.1 0.30000000000000004  1.0" rgba="1.0 0.8550000000000001 0.0 1"/>
         <freejoint/>
        </body>
    <body pos="2.6324243089311334 5.895403622973016 1.0" euler="0 0 1235.9382123914045" >
         <geom type="box" size="0.1 0.30000000000000004  1.0" rgba="1.0 0.8699999999999999 0.0 1"/>
         <freejoint/>
        </body>
    <body pos="1.3097940978713412 6.37159258698738 1.0" euler="0 0 1248.3836582536023" >
         <geom type="box" size="0.1 0.30000000000000004  1.0" rgba="1.0 0.885 0.0 1"/>
         <freejoint/>
        </body>
    <body pos="-0.08523077534779282 6.552343863405199 1.0" euler="0 0 1260.745242987949" >
         <geom type="box" size="0.1 0.30000000000000004  1.0" rgba="1.0 0.8999999999999999 0.0 1"/>
         <freejoint/>
        </body>
    <body pos="-1.4862656116515038 6.431097296276793 1.0" euler="0 0 1273.0129390027269" >
         <geom type="box" size="0.1 0.30000000000000004  1.0" rgba="1.0 0.915 0.0 1"/>
         <freejoint/>
        </body>
    <body pos="-2.829865703935163 6.015597843823004 1.0" euler="0 0 1285.1932952598615" >
         <geom type="box" size="0.1 0.30000000000000004  1.0" rgba="1.0 0.9299999999999999 0.0 1"/>
         <freejoint/>
        </body>
    <body pos="-4.056536995142491 5.326157592433874 1.0" euler="0 0 1297.2938201699835" >
         <geom type="box" size="0.1 0.30000000000000004  1.0" rgba="1.0 0.9450000000000001 0.0 1"/>
         <freejoint/>
        </body>
    <body pos="-5.1111470293660854 4.3962489747204625 1.0" euler="0 0 1309.3001999008209" >
         <geom type="box" size="0.1 0.30000000000000004  1.0" rgba="1.0 0.96 0.0 1"/>
         <freejoint/>
        </body>
    <body pos="-5.950188358421132 3.26707677888409 1.0" euler="0 0 1321.2300814360638" >
         <geom type="box" size="0.1 0.30000000000000004  1.0" rgba="1.0 0.9750000000000001 0.0 1"/>
         <freejoint/>
        </body>
    <body pos="-6.538408951234089 1.988859886624338 1.0" euler="0 0 1333.0812345464315" >
         <geom type="box" size="0.1 0.30000000000000004  1.0" rgba="1.0 0.99 0.0 1"/>
         <freejoint/>
        </body>
    <body pos="-6.852151350155915 0.6179541636136552 1.0" euler="0 0 1344.8467800027452" >
         <geom type="box" size="0.1 0.30000000000000004  1.0" rgba="0.9949999999999999 1.0 0.0 1"/>
         <freejoint/>
        </body>
    <body pos="-6.880369543980357 -0.7887496740462164 1.0" euler="0 0 1356.5397077033913" >
         <geom type="box" size="0.1 0.30000000000000004  1.0" rgba="0.98 1.0 0.0 1"/>
         <freejoint/>
        </body>
    <body pos="-6.623472192374199 -2.1723487487116953 1.0" euler="0 0 1368.1583179157337" >
         <geom type="box" size="0.1 0.30000000000000004  1.0" rgba="0.9649999999999999 1.0 0.0 1"/>
         <freejoint/>
        </body>
    <body pos="-6.094123171520046 -3.475438903407931 1.0" euler="0 0 1379.695831590142" >
         <geom type="box" size="0.1 0.30000000000000004  1.0" rgba="0.95 1.0 0.0 1"/>
         <freejoint/>
        </body>
    <body pos="-5.315005865730232 -4.6470950057955225 1.0" euler="0 0 1391.1643343746337" >
         <geom type="box" size="0.1 0.30000000000000004  1.0" rgba="0.935 1.0 0.0 1"/>
         <freejoint/>
        </body>
    <body pos="-4.318516685068715 -5.641203722008179 1.0" euler="0 0 1402.56482173739" >
         <geom type="box" size="0.1 0.30000000000000004  1.0" rgba="0.9199999999999999 1.0 0.0 1"/>
         <freejoint/>
        </body>
    <body pos="-3.146315100856967 -6.418803858877997 1.0" euler="0 0 1413.8872200190212" >
         <geom type="box" size="0.1 0.30000000000000004  1.0" rgba="0.905 1.0 0.0 1"/>
         <freejoint/>
        </body>
    <body pos="-1.844148557466144 -6.9517753429986575 1.0" euler="0 0 1425.1429255685835" >
         <geom type="box" size="0.1 0.30000000000000004  1.0" rgba="0.8900000000000001 1.0 0.0 1"/>
         <freejoint/>
        </body>
    <body pos="-0.4626660051329258 -7.220935986496763 1.0" euler="0 0 1436.333907024274" >
         <geom type="box" size="0.1 0.30000000000000004  1.0" rgba="0.875 1.0 0.0 1"/>
         <freejoint/>
        </body>
    <body pos="0.9447887823218696 -7.2174271107384085 1.0" euler="0 0 1447.457830703085" >
         <geom type="box" size="0.1 0.30000000000000004  1.0" rgba="0.8599999999999999 1.0 0.0 1"/>
         <freejoint/>
        </body>
    <body pos="2.3247005552035436 -6.943147364433182 1.0" euler="0 0 1458.511546336619" >
         <geom type="box" size="0.1 0.30000000000000004  1.0" rgba="0.845 1.0 0.0 1"/>
         <freejoint/>
        </body>
    <body pos="3.6269732000258403 -6.409711806823742 1.0" euler="0 0 1469.503607285614" >
         <geom type="box" size="0.1 0.30000000000000004  1.0" rgba="0.8300000000000001 1.0 0.0 1"/>
         <freejoint/>
        </body>
    <body pos="4.804215755313069 -5.637979662208297 1.0" euler="0 0 1480.4348660685846" >
         <geom type="box" size="0.1 0.30000000000000004  1.0" rgba="0.815 1.0 0.0 1"/>
         <freejoint/>
        </body>
    <body pos="5.814122188075068 -4.657385918933871 1.0" euler="0 0 1491.303627261584" >
         <geom type="box" size="0.1 0.30000000000000004  1.0" rgba="0.7999999999999998 1.0 0.0 1"/>
         <freejoint/>
        </body>
    <body pos="6.6211582059979825 -3.5047428175677435 1.0" euler="0 0 1502.10662388679" >
         <geom type="box" size="0.1 0.30000000000000004  1.0" rgba="0.7849999999999999 1.0 0.0 1"/>
         <freejoint/>
        </body>
    <body pos="7.198414318228148 -2.221175235226419 1.0" euler="0 0 1512.8516304006835" >
         <geom type="box" size="0.1 0.30000000000000004  1.0" rgba="0.77 1.0 0.0 1"/>
         <freejoint/>
        </body>
    <body pos="7.5267715143912675 -0.8523205808492748 1.0" euler="0 0 1523.5394306122762" >
         <geom type="box" size="0.1 0.30000000000000004  1.0" rgba="0.7549999999999999 1.0 0.0 1"/>
         <freejoint/>
        </body>
    <body pos="7.596049566945018 0.5539262953796047 1.0" euler="0 0 1534.1707942736246" >
         <geom type="box" size="0.1 0.30000000000000004  1.0" rgba="0.74 1.0 0.0 1"/>
         <freejoint/>
        </body>
    <body pos="7.405289695473952 1.9484180141670808 1.0" euler="0 0 1544.7410849592993" >
         <geom type="box" size="0.1 0.30000000000000004  1.0" rgba="0.7250000000000001 1.0 0.0 1"/>
         <freejoint/>
        </body>
    <body pos="6.9624443972893015 3.284329238588518 1.0" euler="0 0 1555.2542226087564" >
         <geom type="box" size="0.1 0.30000000000000004  1.0" rgba="0.71 1.0 0.0 1"/>
         <freejoint/>
        </body>
    <body pos="6.283560684257428 4.517434727811123 1.0" euler="0 0 1565.7134576585604" >
         <geom type="box" size="0.1 0.30000000000000004  1.0" rgba="0.6950000000000001 1.0 0.0 1"/>
         <freejoint/>
        </body>
    <body pos="5.392310005393373 5.60725738514801 1.0" euler="0 0 1576.1194995183112" >
         <geom type="box" size="0.1 0.30000000000000004  1.0" rgba="0.6799999999999999 1.0 0.0 1"/>
         <freejoint/>
        </body>
    <body pos="4.319003222728745 6.518636929115534 1.0" euler="0 0 1586.473045207659" >
         <geom type="box" size="0.1 0.30000000000000004  1.0" rgba="0.665 1.0 0.0 1"/>
         <freejoint/>
        </body>
    <body pos="3.0996843922568553 7.222631106497213 1.0" euler="0 0 1596.7727915682071" >
         <geom type="box" size="0.1 0.30000000000000004  1.0" rgba="0.6499999999999999 1.0 0.0 1"/>
         <freejoint/>
        </body>
    <body pos="1.7747023917556568 7.69757794782254 1.0" euler="0 0 1607.0171273550136" >
         <geom type="box" size="0.1 0.30000000000000004  1.0" rgba="0.635 1.0 0.0 1"/>
         <freejoint/>
        </body>
    <body pos="0.3862679474310301 7.929752669742055 1.0" euler="0 0 1617.2112568307143" >
         <geom type="box" size="0.1 0.30000000000000004  1.0" rgba="0.6199999999999999 1.0 0.0 1"/>
         <freejoint/>
        </body>
    <body pos="-1.0215085872083653 7.9129434229881594 1.0" euler="0 0 1627.3558238324051" >
         <geom type="box" size="0.1 0.30000000000000004  1.0" rgba="0.605 1.0 0.0 1"/>
         <freejoint/>
        </body>
    <body pos="-2.4045401286914974 7.648815247549718 1.0" euler="0 0 1637.4514612390617" >
         <geom type="box" size="0.1 0.30000000000000004  1.0" rgba="0.5899999999999999 1.0 0.0 1"/>
         <freejoint/>
        </body>
    <body pos="-3.720129977604903 7.146671321757863 1.0" euler="0 0 1647.4987912036042" >
         <geom type="box" size="0.1 0.30000000000000004  1.0" rgba="0.575 1.0 0.0 1"/>
         <freejoint/>
        </body>
    <body pos="-4.928250824531662 6.4229870015098 1.0" euler="0 0 1657.498425379093" >
         <geom type="box" size="0.1 0.30000000000000004  1.0" rgba="0.56 1.0 0.0 1"/>
         <freejoint/>
        </body>
    <body pos="-5.992386028013523 5.501064608232536 1.0" euler="0 0 1667.4477866596685" >
         <geom type="box" size="0.1 0.30000000000000004  1.0" rgba="0.5449999999999999 1.0 0.0 1"/>
         <freejoint/>
        </body>
    <body pos="-6.881478393427009 4.409488422414816 1.0" euler="0 0 1677.3492129730637" >
         <geom type="box" size="0.1 0.30000000000000004  1.0" rgba="0.53 1.0 0.0 1"/>
         <freejoint/>
        </body>
    <body pos="-7.570018045950242 3.1813735729820927 1.0" euler="0 0 1687.20494654067" >
         <geom type="box" size="0.1 0.30000000000000004  1.0" rgba="0.5150000000000001 1.0 0.0 1"/>
         <freejoint/>
        </body>
    <body pos="-8.038574131394656 1.8535526856881834 1.0" euler="0 0 1697.0155539655632" >
         <geom type="box" size="0.1 0.30000000000000004  1.0" rgba="0.5 1.0 0.0 1"/>
         <freejoint/>
        </body>
    <body pos="-8.274412775689003 0.46527818119205533 1.0" euler="0 0 1706.7815925241912" >
         <geom type="box" size="0.1 0.30000000000000004  1.0" rgba="0.4849999999999999 1.0 0.0 1"/>
         <freejoint/>
        </body>
    <body pos="-8.27171623805929 -0.9429710137791147 1.0" euler="0 0 1716.5036103574291" >
         <geom type="box" size="0.1 0.30000000000000004  1.0" rgba="0.47 1.0 0.0 1"/>
         <freejoint/>
        </body>
    <body pos="-8.031596049568064 -2.330680720469105 1.0" euler="0 0 1726.1821466569572" >
         <geom type="box" size="0.1 0.30000000000000004  1.0" rgba="0.45500000000000007 1.0 0.0 1"/>
         <freejoint/>
        </body>
    <body pos="-7.561908015674489 -3.6584567518275404 1.0" euler="0 0 1735.8177318470962" >
         <geom type="box" size="0.1 0.30000000000000004  1.0" rgba="0.43999999999999995 1.0 0.0 1"/>
         <freejoint/>
        </body>
    <body pos="-6.876882203920102 -4.889112849637207 1.0" euler="0 0 1745.41088776223" >
         <geom type="box" size="0.1 0.30000000000000004  1.0" rgba="0.4249999999999998 1.0 0.0 1"/>
         <freejoint/>
        </body>
    <body pos="-5.9967084848320305 -5.98853374170428 1.0" euler="0 0 1754.9609204221042" >
         <geom type="box" size="0.1 0.30000000000000004  1.0" rgba="0.4099999999999999 1.0 0.0 1"/>
         <freejoint/>
        </body>
    <body pos="-4.94672014772762 -6.926834268482047 1.0" euler="0 0 1764.467901674483" >
         <geom type="box" size="0.1 0.30000000000000004  1.0" rgba="0.395 1.0 0.0 1"/>
         <freejoint/>
        </body>
    <body pos="-3.7563014087626985 -7.679148579797944 1.0" euler="0 0 1773.934155111566" >
         <geom type="box" size="0.1 0.30000000000000004  1.0" rgba="0.3799999999999999 1.0 0.0 1"/>
         <freejoint/>
        </body>
    <body pos="-2.458436819270066 -8.225769555418335 1.0" euler="0 0 1783.3601657446416" >
         <geom type="box" size="0.1 0.30000000000000004  1.0" rgba="0.36499999999999977 1.0 0.0 1"/>
         <freejoint/>
        </body>
    <body pos="-1.088596972107204 -8.552791765956432 1.0" euler="0 0 1792.7464109165185" >
         <geom type="box" size="0.1 0.30000000000000004  1.0" rgba="0.34999999999999987 1.0 0.0 1"/>
         <freejoint/>
        </body>
    <body pos="0.31626374043725813 -8.6523626923049 1.0" euler="0 0 1802.0933604524414" >
         <geom type="box" size="0.1 0.30000000000000004  1.0" rgba="0.33499999999999996 1.0 0.0 1"/>
         <freejoint/>
        </body>
    <body pos="1.718719614366356 -8.522765681625033 1.0" euler="0 0 1811.4014768074562" >
         <geom type="box" size="0.1 0.30000000000000004  1.0" rgba="0.31999999999999984 1.0 0.0 1"/>
         <freejoint/>
        </body>
    <body pos="3.081869258019572 -8.168338725826995 1.0" euler="0 0 1820.6712152103266" >
         <geom type="box" size="0.1 0.30000000000000004  1.0" rgba="0.3049999999999997 1.0 0.0 1"/>
         <freejoint/>
        </body>
    <body pos="4.370288915730658 -7.599237266978592 1.0" euler="0 0 1829.9030238040898" >
         <geom type="box" size="0.1 0.30000000000000004  1.0" rgba="0.2899999999999998 1.0 0.0 1"/>
         <freejoint/>
        </body>
    <body pos="5.550920300065243 -6.831052918824221 1.0" euler="0 0 1839.0973437833468" >
         <geom type="box" size="0.1 0.30000000000000004  1.0" rgba="0.2749999999999999 1.0 0.0 1"/>
         <freejoint/>
        </body>
    <body pos="6.593872467014342 -5.884303175865996 1.0" euler="0 0 1848.254609528373" >
         <geom type="box" size="0.1 0.30000000000000004  1.0" rgba="0.26000000000000023 1.0 0.0 1"/>
         <freejoint/>
        </body>
    <body pos="7.473120374455962 -4.783809810244597 1.0" euler="0 0 1857.3752487361362" >
         <geom type="box" size="0.1 0.30000000000000004  1.0" rgba="0.2450000000000001 1.0 0.0 1"/>
         <freejoint/>
        </body>
    <body pos="8.167086148582042 -3.5579856985884866 1.0" euler="0 0 1866.4596825483027" >
         <geom type="box" size="0.1 0.30000000000000004  1.0" rgba="0.22999999999999998 1.0 0.0 1"/>
         <freejoint/>
        </body>
    <body pos="8.65909264369298 -2.2380512598341906 1.0" euler="0 0 1875.5083256763146" >
         <geom type="box" size="0.1 0.30000000000000004  1.0" rgba="0.21500000000000008 1.0 0.0 1"/>
         <freejoint/>
        </body>
    <body pos="8.93768251816995 -0.8572025207476374 1.0" euler="0 0 1884.5215865236164" >
         <geom type="box" size="0.1 0.30000000000000004  1.0" rgba="0.20000000000000018 1.0 0.0 1"/>
         <freejoint/>
        </body>
    <body pos="8.99679966874437 0.5502469265126626 1.0" euler="0 0 1893.4998673051016" >
         <geom type="box" size="0.1 0.30000000000000004  1.0" rgba="0.18500000000000005 1.0 0.0 1"/>
         <freejoint/>
        </body>
    <body pos="8.835833378386083 1.9497281224665617 1.0" euler="0 0 1902.4435641638588" >
         <geom type="box" size="0.1 0.30000000000000004  1.0" rgba="0.16999999999999993 1.0 0.0 1"/>
         <freejoint/>
        </body>
    <body pos="8.459528860663372 3.307261973047217 1.0" euler="0 0 1911.3530672852855" >
         <geom type="box" size="0.1 0.30000000000000004  1.0" rgba="0.15500000000000003 1.0 0.0 1"/>
         <freejoint/>
        </body>
    <body pos="7.877770955481867 4.590267696502058 1.0" euler="0 0 1920.2287610086353" >
         <geom type="box" size="0.1 0.30000000000000004  1.0" rgba="0.14000000000000012 1.0 0.0 1"/>
         <freejoint/>
        </body>
    <body pos="7.105250488595532 5.768316375325131 1.0" euler="0 0 1929.0710239360737" >
         <geom type="box" size="0.1 0.30000000000000004  1.0" rgba="0.125 1.0 0.0 1"/>
         <freejoint/>
        </body>
    <body pos="6.161025202465087 6.813813562098811 1.0" euler="0 0 1937.8802290393012" >
         <geom type="box" size="0.1 0.30000000000000004  1.0" rgba="0.10999999999999988 1.0 0.0 1"/>
         <freejoint/>
        </body>
    <body pos="5.067989162834694 7.702597224489199 1.0" euler="0 0 1946.6567437638025" >
         <geom type="box" size="0.1 0.30000000000000004  1.0" rgba="0.09499999999999997 1.0 0.0 1"/>
         <freejoint/>
        </body>
    <body pos="3.8522661193984304 8.414439858890484 1.0" euler="0 0 1955.4009301307983" >
         <geom type="box" size="0.1 0.30000000000000004  1.0" rgba="0.08000000000000007 1.0 0.0 1"/>
         <freejoint/>
        </body>
    <body pos="2.542543437125153 8.93344628353375 1.0" euler="0 0 1964.1131448369413" >
         <geom type="box" size="0.1 0.30000000000000004  1.0" rgba="0.06499999999999995 1.0 0.0 1"/>
         <freejoint/>
        </body>
    <body pos="1.1693639150919743 9.248341370746191 1.0" euler="0 0 1972.7937393518223" >
         <geom type="box" size="0.1 0.30000000000000004  1.0" rgba="0.04999999999999982 1.0 0.0 1"/>
         <freejoint/>
        </body>
    <body pos="-0.2356069198932348 9.3526447277597 1.0" euler="0 0 1981.443060013348" >
         <geom type="box" size="0.1 0.30000000000000004  1.0" rgba="0.03499999999999992 1.0 0.0 1"/>
         <freejoint/>
        </body>
    <body pos="-1.6403205996702883 9.244732023448579 1.0" euler="0 0 1990.061448121032" >
         <geom type="box" size="0.1 0.30000000000000004  1.0" rgba="0.020000000000000018 1.0 0.0 1"/>
         <freejoint/>
        </body>
    <body pos="-3.0130756648885075 8.927785227314137 1.0" euler="0 0 1998.6492400272625" >
         <geom type="box" size="0.1 0.30000000000000004  1.0" rgba="0.004999999999999893 1.0 0.0 1"/>
         <freejoint/>
        </body>
    <body pos="-4.323221745942703 8.409636425796219 1.0" euler="0 0 2007.2067672265903" >
         <geom type="box" size="0.1 0.30000000000000004  1.0" rgba="0.0 1.0 0.010000000000000231 1"/>
         <freejoint/>
        </body>
    <body pos="-5.541822940535147 7.702512065350703 1.0" euler="0 0 2015.7343564430953" >
         <geom type="box" size="0.1 0.30000000000000004  1.0" rgba="0.0 1.0 0.025000000000000355 1"/>
         <freejoint/>
        </body>
    <body pos="-6.642267124999904 6.822686404864023 1.0" euler="0 0 2024.2323297158691" >
         <geom type="box" size="0.1 0.30000000000000004  1.0" rgba="0.0 1.0 0.040000000000000036 1"/>
         <freejoint/>
        </body>
    <body pos="-7.6008095336561485 5.790054612772372 1.0" euler="0 0 2032.7010044826718" >
         <geom type="box" size="0.1 0.30000000000000004  1.0" rgba="0.0 1.0 0.05500000000000016 1"/>
         <freejoint/>
        </body>
    <body pos="-8.397040814699128 4.627637295439459 1.0" euler="0 0 2041.1406936617968" >
         <geom type="box" size="0.1 0.30000000000000004  1.0" rgba="0.0 1.0 0.07000000000000028 1"/>
         <freejoint/>
        </body>
    <body pos="-9.01427177283052 3.361029279414749 1.0" euler="0 0 2049.5517057322045" >
         <geom type="box" size="0.1 0.30000000000000004  1.0" rgba="0.0 1.0 0.08499999999999996 1"/>
         <freejoint/>
        </body>
    <body pos="-9.439829088487793 2.017806185189537 1.0" euler="0 0 2057.9343448119434" >
         <geom type="box" size="0.1 0.30000000000000004  1.0" rgba="0.0 1.0 0.10000000000000009 1"/>
         <freejoint/>
        </body>
    <body pos="-9.665258412906972 0.6269027252026753 1.0" euler="0 0 2066.2889107349292" >
         <geom type="box" size="0.1 0.30000000000000004  1.0" rgba="0.0 1.0 0.11499999999999977 1"/>
         <freejoint/>
        </body>
    <body pos="-9.686433331246702 -0.7820232579581665 1.0" euler="0 0 2074.615699126097" >
         <geom type="box" size="0.1 0.30000000000000004  1.0" rgba="0.0 1.0 0.1299999999999999 1"/>
         <freejoint/>
        </body>
    <body pos="-9.503570719526648 -2.1792272119804954 1.0" euler="0 0 2082.915001474984" >
         <geom type="box" size="0.1 0.30000000000000004  1.0" rgba="0.0 1.0 0.14500000000000002 1"/>
         <freejoint/>
        </body>
    <body pos="-9.121154955783703 -3.53550144600688 1.0" euler="0 0 2091.187105207773" >
         <geom type="box" size="0.1 0.30000000000000004  1.0" rgba="0.0 1.0 0.16000000000000014 1"/>
         <freejoint/>
        </body>
    <body pos="-8.5477752465069 -4.822773292504592 1.0" euler="0 0 2099.4322937578327" >
         <geom type="box" size="0.1 0.30000000000000004  1.0" rgba="0.0 1.0 0.17499999999999982 1"/>
         <freejoint/>
        </body>
    <body pos="-7.795881965679842 -6.014666274104155 1.0" euler="0 0 2107.650846634794" >
         <geom type="box" size="0.1 0.30000000000000004  1.0" rgba="0.0 1.0 0.18999999999999995 1"/>
         <freejoint/>
        </body>
    <body pos="-6.88146935029258 -7.0870138595895344 1.0" euler="0 0 2115.843039492203" >
         <geom type="box" size="0.1 0.30000000000000004  1.0" rgba="0.0 1.0 0.20500000000000007 1"/>
         <freejoint/>
        </body>
    <body pos="-5.82375306992459 -8.018271100200007 1.0" euler="0 0 2124.0087087955962" >
         <geom type="box" size="0.1 0.30000000000000004  1.0" rgba="0.0 1.0 0.21999999999999975 1"/>
         <freejoint/>
        </body>
    <body pos="-4.644840791101326 -8.789908426200524 1.0" euler="0 0 2132.1467369737456" >
         <geom type="box" size="0.1 0.30000000000000004  1.0" rgba="0.0 1.0 0.23499999999999988 1"/>
         <freejoint/>
        </body>
    <body pos="-3.36862413522081 -9.387102196790888 1.0" euler="0 0 2140.2591375005113" >
         <geom type="box" size="0.1 0.30000000000000004  1.0" rgba="0.0 1.0 0.25 1"/>
         <freejoint/>
        </body>
    <body pos="-2.020926306904841 -9.798442222344768 1.0" euler="0 0 2148.3461728835427" >
         <geom type="box" size="0.1 0.30000000000000004  1.0" rgba="0.0 1.0 0.2650000000000001 1"/>
         <freejoint/>
        </body>
    <body pos="-0.6287512554717215 -10.016316702680294 1.0" euler="0 0 2156.4081020581775" >
         <geom type="box" size="0.1 0.30000000000000004  1.0" rgba="0.0 1.0 0.28000000000000025 1"/>
         <freejoint/>
        </body>
    <body pos="0.7802673569830217 -10.03700386688561 1.0" euler="0 0 2164.4451804479913" >
         <geom type="box" size="0.1 0.30000000000000004  1.0" rgba="0.0 1.0 0.29499999999999993 1"/>
         <freejoint/>
        </body>
    <body pos="2.178417677410657 -9.860685434611616 1.0" euler="0 0 2172.457660024119" >
         <geom type="box" size="0.1 0.30000000000000004  1.0" rgba="0.0 1.0 0.31000000000000005 1"/>
         <freejoint/>
        </body>
    <body pos="3.53845093539941 -9.491383789674435 1.0" euler="0 0 2180.4457893633758" >
         <geom type="box" size="0.1 0.30000000000000004  1.0" rgba="0.0 1.0 0.3250000000000002 1"/>
         <freejoint/>
        </body>
    <body pos="4.834102288213314 -8.936826165474363 1.0" euler="0 0 2188.409813705211" >
         <geom type="box" size="0.1 0.30000000000000004  1.0" rgba="0.0 1.0 0.33999999999999986 1"/>
         <freejoint/>
        </body>
    <body pos="6.040581787639137 -8.208240431593888 1.0" euler="0 0 2196.3499750075175" >
         <geom type="box" size="0.1 0.30000000000000004  1.0" rgba="0.0 1.0 0.355 1"/>
         <freejoint/>
        </body>
    <body pos="7.135026900786481 -7.3200882228960955 1.0" euler="0 0 2204.266512001327" >
         <geom type="box" size="0.1 0.30000000000000004  1.0" rgba="0.0 1.0 0.3700000000000001 1"/>
         <freejoint/>
        </body>
    <body pos="8.09690902643603 -6.289742150995436 1.0" euler="0 0 2212.159660244412" >
         <geom type="box" size="0.1 0.30000000000000004  1.0" rgba="0.0 1.0 0.38500000000000023 1"/>
         <freejoint/>
        </body>
    <body pos="8.908117707453686 -5.137560023241144 1.0" euler="0 0 2220.0267515298337" >
         <geom type="box" size="0.1 0.30000000000000004  1.0" rgba="0.0 1.0 0.40000000000000036 1"/>
         <freejoint/>
        </body>
    <body pos="9.554175101711067 -3.885244907390733 1.0" euler="0 0 2227.8706788973127" >
         <geom type="box" size="0.1 0.30000000000000004  1.0" rgba="0.0 1.0 0.41500000000000004 1"/>
         <freejoint/>
        </body>
    <body pos="10.02348137914815 -2.5564715766656394 1.0" euler="0 0 2235.6918514190897" >
         <geom type="box" size="0.1 0.30000000000000004  1.0" rgba="0.0 1.0 0.43000000000000016 1"/>
         <freejoint/>
        </body>
    <body pos="10.307800278453533 -1.1761579518852177 1.0" euler="0 0 2243.4904937457313" >
         <geom type="box" size="0.1 0.30000000000000004  1.0" rgba="0.0 1.0 0.4450000000000003 1"/>
         <freejoint/>
        </body>
    <body pos="10.402383348359939 0.23003743195992074 1.0" euler="0 0 2251.2668275808305" >
         <geom type="box" size="0.1 0.30000000000000004  1.0" rgba="0.0 1.0 0.45999999999999996 1"/>
         <freejoint/>
        </body>
    <body pos="10.306007721994376 1.6361968236918276 1.0" euler="0 0 2259.021071729163" >
         <geom type="box" size="0.1 0.30000000000000004  1.0" rgba="0.0 1.0 0.4750000000000001 1"/>
         <freejoint/>
        </body>
    <body pos="10.020948894388887 3.0166198625396263 1.0" euler="0 0 2266.753442143899" >
         <geom type="box" size="0.1 0.30000000000000004  1.0" rgba="0.0 1.0 0.4900000000000002 1"/>
         <freejoint/>
        </body>
    <body pos="9.552890642068007 4.346286893499014 1.0" euler="0 0 2274.464151972903" >
         <geom type="box" size="0.1 0.30000000000000004  1.0" rgba="0.0 1.0 0.5049999999999999 1"/>
         <freejoint/>
        </body>
    <body pos="8.910875879482344 5.601133179249006 1.0" euler="0 0 2282.152346750949" >
         <geom type="box" size="0.1 0.30000000000000004  1.0" rgba="0.0 1.0 0.52 1"/>
         <freejoint/>
        </body>
    <body pos="8.107140831120297 6.758622151671883 1.0" euler="0 0 2289.8167116189907" >
         <geom type="box" size="0.1 0.30000000000000004  1.0" rgba="0.0 1.0 0.5350000000000001 1"/>
         <freejoint/>
        </body>
    <body pos="7.1562766189756495 7.798766314714356 1.0" euler="0 0 2297.4599946274716" >
         <geom type="box" size="0.1 0.30000000000000004  1.0" rgba="0.0 1.0 0.5499999999999998 1"/>
         <freejoint/>
        </body>
    <body pos="6.0755499641108734 8.703397746949992 1.0" euler="0 0 2305.0823992271985" >
         <geom type="box" size="0.1 0.30000000000000004  1.0" rgba="0.0 1.0 0.565 1"/>
         <freejoint/>
        </body>
    <body pos="4.88438131185186 9.456886015944683 1.0" euler="0 0 2312.684126259932" >
         <geom type="box" size="0.1 0.30000000000000004  1.0" rgba="0.0 1.0 0.5800000000000001 1"/>
         <freejoint/>
        </body>
    <body pos="3.603975456593446 10.046378293391472 1.0" euler="0 0 2320.2653740000683" >
         <geom type="box" size="0.1 0.30000000000000004  1.0" rgba="0.0 1.0 0.5949999999999998 1"/>
         <freejoint/>
        </body>
    <body pos="2.256928006061763 10.461986611173407 1.0" euler="0 0 2327.826338195526" >
         <geom type="box" size="0.1 0.30000000000000004  1.0" rgba="0.0 1.0 0.6099999999999999 1"/>
         <freejoint/>
        </body>
    <body pos="0.8668150664580935 10.696920289874576 1.0" euler="0 0 2335.3672121078516" >
         <geom type="box" size="0.1 0.30000000000000004  1.0" rgba="0.0 1.0 0.625 1"/>
         <freejoint/>
        </body>
    <body pos="-0.5415273836391266 10.747583317130223 1.0" euler="0 0 2342.88446396083" >
         <geom type="box" size="0.1 0.30000000000000004  1.0" rgba="0.0 1.0 0.6400000000000001 1"/>
         <freejoint/>
        </body>
    <body pos="-1.9444672673381072 10.61372682827962 1.0" euler="0 0 2350.381636435139" >
         <geom type="box" size="0.1 0.30000000000000004  1.0" rgba="0.0 1.0 0.6550000000000002 1"/>
         <freejoint/>
        </body>
    <body pos="-3.3181066329887026 10.298093202858842 1.0" euler="0 0 2357.8592480688526" >
         <geom type="box" size="0.1 0.30000000000000004  1.0" rgba="0.0 1.0 0.6699999999999999 1"/>
         <freejoint/>
        </body>
    <body pos="-4.639165962359833 9.806485397697342 1.0" euler="0 0 2365.3174834801243" >
         <geom type="box" size="0.1 0.30000000000000004  1.0" rgba="0.0 1.0 0.685 1"/>
         <freejoint/>
        </body>
    <body pos="-5.8854301955576425 9.147636207187013 1.0" euler="0 0 2372.756524971488" >
         <geom type="box" size="0.1 0.30000000000000004  1.0" rgba="0.0 1.0 0.7000000000000002 1"/>
         <freejoint/>
        </body>
    <body pos="-7.036108263770422 8.333024559560887 1.0" euler="0 0 2380.1765525660385" >
         <geom type="box" size="0.1 0.30000000000000004  1.0" rgba="0.0 1.0 0.7149999999999999 1"/>
         <freejoint/>
        </body>
    <body pos="-8.07197017160433 7.376851319718617 1.0" euler="0 0 2387.5762827060316" >
         <geom type="box" size="0.1 0.30000000000000004  1.0" rgba="0.0 1.0 0.73 1"/>
         <freejoint/>
        </body>
    <body pos="-8.975940093806651 6.295670838048015 1.0" euler="0 0 2394.954409325679" >
         <geom type="box" size="0.1 0.30000000000000004  1.0" rgba="0.0 1.0 0.7450000000000001 1"/>
         <freejoint/>
        </body>
    <body pos="-9.733790858002376 5.107316792192401 1.0" euler="0 0 2402.314018707749" >
         <geom type="box" size="0.1 0.30000000000000004  1.0" rgba="0.0 1.0 0.7600000000000002 1"/>
         <freejoint/>
        </body>
    <body pos="-10.333375688082647 3.831602714239241 1.0" euler="0 0 2409.655282916198" >
         <geom type="box" size="0.1 0.30000000000000004  1.0" rgba="0.0 1.0 0.7750000000000004 1"/>
         <freejoint/>
        </body>
    <body pos="-10.765226923077837 2.489629110960926 1.0" euler="0 0 2416.9783718901044" >
         <geom type="box" size="0.1 0.30000000000000004  1.0" rgba="0.0 1.0 0.79 1"/>
         <freejoint/>
        </body>
    <body pos="-11.022677532230892 1.1034245429146674 1.0" euler="0 0 2424.2834534763615" >
         <geom type="box" size="0.1 0.30000000000000004  1.0" rgba="0.0 1.0 0.8050000000000002 1"/>
         <freejoint/>
        </body>
    <body pos="-11.10193732365787 -0.3041480056976533 1.0" euler="0 0 2431.569279199345" >
         <geom type="box" size="0.1 0.30000000000000004  1.0" rgba="0.0 1.0 0.8200000000000003 1"/>
         <freejoint/>
        </body>
    <body pos="-11.002268215629567 -1.709958088725592 1.0" euler="0 0 2438.834157728017" >
         <geom type="box" size="0.1 0.30000000000000004  1.0" rgba="0.0 1.0 0.835 1"/>
         <freejoint/>
        </body>
    <body pos="-10.725734124204015 -3.0920717537099742 1.0" euler="0 0 2446.081495229636" >
         <geom type="box" size="0.1 0.30000000000000004  1.0" rgba="0.0 1.0 0.8500000000000001 1"/>
         <freejoint/>
        </body>
    <body pos="-10.277132232653097 -4.428467781681596 1.0" euler="0 0 2453.3114522132005" >
         <geom type="box" size="0.1 0.30000000000000004  1.0" rgba="0.0 1.0 0.8650000000000002 1"/>
         <freejoint/>
        </body>
    <body pos="-9.66395898580898 -5.698003375739815 1.0" euler="0 0 2460.5241872356273" >
         <geom type="box" size="0.1 0.30000000000000004  1.0" rgba="0.0 1.0 0.8799999999999999 1"/>
         <freejoint/>
        </body>
    <body pos="-8.896260361755813 -6.880737607588719 1.0" euler="0 0 2467.719856931335" >
         <geom type="box" size="0.1 0.30000000000000004  1.0" rgba="0.0 1.0 0.895 1"/>
         <freejoint/>
        </body>
    <body pos="-7.9869054450829795 -7.957749614410988 1.0" euler="0 0 2474.8952310866803" >
         <geom type="box" size="0.1 0.30000000000000004  1.0" rgba="0.0 1.0 0.9100000000000001 1"/>
         <freejoint/>
        </body>
    <body pos="-6.950335203161996 -8.91278100809331 1.0" euler="0 0 2482.0523004532174" >
         <geom type="box" size="0.1 0.30000000000000004  1.0" rgba="0.0 1.0 0.9249999999999998 1"/>
         <freejoint/>
        </body>
    <body pos="-5.802777643680492 -9.731447358546495 1.0" euler="0 0 2489.1927428176946" >
         <geom type="box" size="0.1 0.30000000000000004  1.0" rgba="0.0 1.0 0.94 1"/>
         <freejoint/>
        </body>
    <body pos="-4.562249030490797 -10.401333461749546 1.0" euler="0 0 2496.3167080414755" >
         <geom type="box" size="0.1 0.30000000000000004  1.0" rgba="0.0 1.0 0.9550000000000001 1"/>
         <freejoint/>
        </body>
    <body pos="-3.2480798463577494 -10.91240020712258 1.0" euler="0 0 2503.4243441906037" >
         <geom type="box" size="0.1 0.30000000000000004  1.0" rgba="0.0 1.0 0.9699999999999998 1"/>
         <freejoint/>
        </body>
    <body pos="-1.881007049288142 -11.257036429586485 1.0" euler="0 0 2510.5137389213824" >
         <geom type="box" size="0.1 0.30000000000000004  1.0" rgba="0.0 1.0 0.9849999999999999 1"/>
         <freejoint/>
        </body>
    <body pos="-0.4822711266507006 -11.430435085738486 1.0" euler="0 0 2517.584018370362" >
         <geom type="box" size="0.1 0.30000000000000004  1.0" rgba="0.0 1.0 1.0 1"/>
         <freejoint/>
        </body>
    <body pos="0.9273824563186976 -11.430479481132927 1.0" euler="0 0 2524.63838567802" >
         <geom type="box" size="0.1 0.30000000000000004  1.0" rgba="0.0 0.9849999999999994 1.0 1"/>
         <freejoint/>
        </body>
    <body pos="2.3266009115802464 -11.257503741051648 1.0" euler="0 0 2531.676982560765" >
         <geom type="box" size="0.1 0.30000000000000004  1.0" rgba="0.0 0.9699999999999998 1.0 1"/>
         <freejoint/>
        </body>
    <body pos="3.694324663620203 -10.914444013540976 1.0" euler="0 0 2538.6999490573407" >
         <geom type="box" size="0.1 0.30000000000000004  1.0" rgba="0.0 0.9549999999999996 1.0 1"/>
         <freejoint/>
        </body>
    <body pos="5.009728313230391 -10.406936340952305 1.0" euler="0 0 2545.7054001019137" >
         <geom type="box" size="0.1 0.30000000000000004  1.0" rgba="0.0 0.94 1.0 1"/>
         <freejoint/>
        </body>
    <body pos="6.253109222214749 -9.743136588587603 1.0" euler="0 0 2552.692198314552" >
         <geom type="box" size="0.1 0.30000000000000004  1.0" rgba="0.0 0.9250000000000003 1.0 1"/>
         <freejoint/>
        </body>
    <body pos="7.406771908745507 -8.932989464472362 1.0" euler="0 0 2559.663762953185" >
         <geom type="box" size="0.1 0.30000000000000004  1.0" rgba="0.0 0.9100000000000001 1.0 1"/>
         <freejoint/>
        </body>
    <body pos="8.453829541100287 -7.98873747316895 1.0" euler="0 0 2566.6202280997168" >
         <geom type="box" size="0.1 0.30000000000000004  1.0" rgba="0.0 0.8950000000000005 1.0 1"/>
         <freejoint/>
        </body>
    <body pos="9.379066313408844 -6.924519581588694 1.0" euler="0 0 2573.5617262673168" >
         <geom type="box" size="0.1 0.30000000000000004  1.0" rgba="0.0 0.8799999999999999 1.0 1"/>
         <freejoint/>
        </body>
    <body pos="10.168811095151892 -5.756704991930713 1.0" euler="0 0 2580.4851979223536" >
         <geom type="box" size="0.1 0.30000000000000004  1.0" rgba="0.0 0.8650000000000002 1.0 1"/>
         <freejoint/>
        </body>
    <body pos="10.812055768471419 -4.502470142841736 1.0" euler="0 0 2587.3916640975335" >
         <geom type="box" size="0.1 0.30000000000000004  1.0" rgba="0.0 0.8499999999999996 1.0 1"/>
         <freejoint/>
        </body>
    <body pos="11.300010346207376 -3.179792463380932 1.0" euler="0 0 2594.2835411661436" >
         <geom type="box" size="0.1 0.30000000000000004  1.0" rgba="0.0 0.835 1.0 1"/>
         <freejoint/>
        </body>
    <body pos="11.625896195786922 -1.8078969575976211 1.0" euler="0 0 2601.160956049204" >
         <geom type="box" size="0.1 0.30000000000000004  1.0" rgba="0.0 0.8199999999999998 1.0 1"/>
         <freejoint/>
        </body>
    <body pos="11.785303725182777 -0.40660226725958726 1.0" euler="0 0 2608.0240341999365" >
         <geom type="box" size="0.1 0.30000000000000004  1.0" rgba="0.0 0.8050000000000002 1.0 1"/>
         <freejoint/>
        </body>
    <body pos="11.77630628269951 1.0028408996210347 1.0" euler="0 0 2614.8674226240623" >
         <geom type="box" size="0.1 0.30000000000000004  1.0" rgba="0.0 0.79 1.0 1"/>
         <freejoint/>
        </body>
    <body pos="11.59951506268989 2.4014169241340104 1.0" euler="0 0 2621.696555830325" >
         <geom type="box" size="0.1 0.30000000000000004  1.0" rgba="0.0 0.7750000000000004 1.0 1"/>
         <freejoint/>
        </body>
    <body pos="11.257718655498174 3.7693390738648436 1.0" euler="0 0 2628.5117123365203" >
         <geom type="box" size="0.1 0.30000000000000004  1.0" rgba="0.0 0.7599999999999998 1.0 1"/>
         <freejoint/>
        </body>
    <body pos="10.756016415198589 5.087334590069317 1.0" euler="0 0 2635.313012342594" >
         <geom type="box" size="0.1 0.30000000000000004  1.0" rgba="0.0 0.7450000000000001 1.0 1"/>
         <freejoint/>
        </body>
    <body pos="10.102051312341242 6.336401302847434 1.0" euler="0 0 2642.0975434700667" >
         <geom type="box" size="0.1 0.30000000000000004  1.0" rgba="0.0 0.7299999999999995 1.0 1"/>
         <freejoint/>
        </body>
    <body pos="9.305385943176924 7.499309679921227 1.0" euler="0 0 2648.865711002988" >
         <geom type="box" size="0.1 0.30000000000000004  1.0" rgba="0.0 0.7149999999999999 1.0 1"/>
         <freejoint/>
        </body>
    <body pos="8.377113704432084 8.560512675770527 1.0" euler="0 0 2655.620368884839" >
         <geom type="box" size="0.1 0.30000000000000004  1.0" rgba="0.0 0.6999999999999997 1.0 1"/>
         <freejoint/>
        </body>
    <body pos="7.330322814001639 9.505444034405809 1.0" euler="0 0 2662.3616323089964" >
         <geom type="box" size="0.1 0.30000000000000004  1.0" rgba="0.0 0.685 1.0 1"/>
         <freejoint/>
        </body>
    <body pos="6.179898297433339 10.321078105559 1.0" euler="0 0 2669.088309754224" >
         <geom type="box" size="0.1 0.30000000000000004  1.0" rgba="0.0 0.6699999999999999 1.0 1"/>
         <freejoint/>
        </body>
    <body pos="4.942514393326062 10.996169711382162 1.0" euler="0 0 2675.7972266495112" >
         <geom type="box" size="0.1 0.30000000000000004  1.0" rgba="0.0 0.6550000000000002 1.0 1"/>
         <freejoint/>
        </body>
    <body pos="3.6344936569767503 11.522290894295317 1.0" euler="0 0 2682.493083331872" >
         <geom type="box" size="0.1 0.30000000000000004  1.0" rgba="0.0 0.6399999999999997 1.0 1"/>
         <freejoint/>
        </body>
    <body pos="2.2737792048707104 11.89249053206902 1.0" euler="0 0 2689.1759902216013" >
         <geom type="box" size="0.1 0.30000000000000004  1.0" rgba="0.0 0.625 1.0 1"/>
         <freejoint/>
        </body>
    <body pos="0.8789890165677952 12.101965404807077 1.0" euler="0 0 2695.845792150294" >
         <geom type="box" size="0.1 0.30000000000000004  1.0" rgba="0.0 0.6099999999999994 1.0 1"/>
         <freejoint/>
        </body>
    <body pos="-0.5297870307357853 12.148164354564939 1.0" euler="0 0 2702.4971130162216" >
         <geom type="box" size="0.1 0.30000000000000004  1.0" rgba="0.0 0.5949999999999998 1.0 1"/>
         <freejoint/>
        </body>
    <body pos="-1.9347585483195544 12.030951969877407 1.0" euler="0 0 2709.135806279137" >
         <geom type="box" size="0.1 0.30000000000000004  1.0" rgba="0.0 0.5799999999999996 1.0 1"/>
         <freejoint/>
        </body>
    <body pos="-3.3170967186647946 11.752133148181104 1.0" euler="0 0 2715.7619778073" >
         <geom type="box" size="0.1 0.30000000000000004  1.0" rgba="0.0 0.565 1.0 1"/>
         <freejoint/>
        </body>
    <body pos="-4.658372227198674 11.315659362433623 1.0" euler="0 0 2722.3757322889455" >
         <geom type="box" size="0.1 0.30000000000000004  1.0" rgba="0.0 0.5499999999999998 1.0 1"/>
         <freejoint/>
        </body>
    <body pos="-5.9396626330033495 10.72815817455513 1.0" euler="0 0 2728.971179394125" >
         <geom type="box" size="0.1 0.30000000000000004  1.0" rgba="0.0 0.5350000000000001 1.0 1"/>
         <freejoint/>
        </body>
    <body pos="-7.145308812221724 9.997302638762998 1.0" euler="0 0 2735.5542899195502" >
         <geom type="box" size="0.1 0.30000000000000004  1.0" rgba="0.0 0.5200000000000005 1.0 1"/>
         <freejoint/>
        </body>
    <body pos="-8.2595452522631 9.132912426826081 1.0" euler="0 0 2742.125290891399" >
         <geom type="box" size="0.1 0.30000000000000004  1.0" rgba="0.0 0.5049999999999999 1.0 1"/>
         <freejoint/>
        </body>
    <body pos="-9.267844900698936 8.146536112694449 1.0" euler="0 0 2748.684178719187" >
         <geom type="box" size="0.1 0.30000000000000004  1.0" rgba="0.0 0.4900000000000002 1.0 1"/>
         <freejoint/>
        </body>
    <body pos="-10.156399565102905 7.0523001910071805 1.0" euler="0 0 2755.2250424468684" >
         <geom type="box" size="0.1 0.30000000000000004  1.0" rgba="0.0 0.47499999999999964 1.0 1"/>
         <freejoint/>
        </body>
    <body pos="-10.91479186679395 5.863723640821658 1.0" euler="0 0 2761.7540962372195" >
         <geom type="box" size="0.1 0.30000000000000004  1.0" rgba="0.0 0.45999999999999996 1.0 1"/>
         <freejoint/>
        </body>
    <body pos="-11.533355584549012 4.596340943597894 1.0" euler="0 0 2768.2714374715706" >
         <geom type="box" size="0.1 0.30000000000000004  1.0" rgba="0.0 0.44499999999999984 1.0 1"/>
         <freejoint/>
        </body>
    <body pos="-12.004220126331317 3.2668205385362867 1.0" euler="0 0 2774.776239942852" >
         <geom type="box" size="0.1 0.30000000000000004  1.0" rgba="0.0 0.43000000000000016 1.0 1"/>
         <freejoint/>
        </body>
    <body pos="-12.321408897452699 1.8933347935854177 1.0" euler="0 0 2781.2641341280237" >
         <geom type="box" size="0.1 0.30000000000000004  1.0" rgba="0.0 0.41500000000000004 1.0 1"/>
         <freejoint/>
        </body>
    <body pos="-12.48150260761071 0.4924494264398468 1.0" euler="0 0 2787.740604803969" >
         <geom type="box" size="0.1 0.30000000000000004  1.0" rgba="0.0 0.40000000000000036 1.0 1"/>
         <freejoint/>
        </body>
    <body pos="-12.482650734941997 -0.9179270401776417 1.0" euler="0 0 2794.205745395817" >
         <geom type="box" size="0.1 0.30000000000000004  1.0" rgba="0.0 0.3849999999999998 1.0 1"/>
         <freejoint/>
        </body>
    <body pos="-12.325114599212368 -2.3193530970646288 1.0" euler="0 0 2800.657347066301" >
         <geom type="box" size="0.1 0.30000000000000004  1.0" rgba="0.0 0.3700000000000001 1.0 1"/>
         <freejoint/>
        </body>
    <body pos="-12.011355163371968 -3.6937317893595147 1.0" euler="0 0 2807.0937092111126" >
         <geom type="box" size="0.1 0.30000000000000004  1.0" rgba="0.0 0.35499999999999954 1.0 1"/>
         <freejoint/>
        </body>
    <body pos="-11.545460486036331 -5.024667056369059 1.0" euler="0 0 2813.5190201955565" >
         <geom type="box" size="0.1 0.30000000000000004  1.0" rgba="0.0 0.33999999999999986 1.0 1"/>
         <freejoint/>
        </body>
    <body pos="-10.933457979980252 -6.2954933114901745 1.0" euler="0 0 2819.9333696669078" >
         <geom type="box" size="0.1 0.30000000000000004  1.0" rgba="0.0 0.32499999999999973 1.0 1"/>
         <freejoint/>
        </body>
    <body pos="-10.18371185937493 -7.489613876200097 1.0" euler="0 0 2826.332633571493" >
         <geom type="box" size="0.1 0.30000000000000004  1.0" rgba="0.0 0.31000000000000005 1.0 1"/>
         <freejoint/>
        </body>
    <body pos="-9.305696148593315 -8.592720160584216 1.0" euler="0 0 2832.718852454293" >
         <geom type="box" size="0.1 0.30000000000000004  1.0" rgba="0.0 0.29499999999999993 1.0 1"/>
         <freejoint/>
        </body>
    <body pos="-8.310206001685932 -9.591662643819681 1.0" euler="0 0 2839.094379049032" >
         <geom type="box" size="0.1 0.30000000000000004  1.0" rgba="0.0 0.28000000000000025 1.0 1"/>
         <freejoint/>
        </body>
    <body pos="-7.2096942169051434 -10.474191784140856 1.0" euler="0 0 2845.4592202602335" >
         <geom type="box" size="0.1 0.30000000000000004  1.0" rgba="0.0 0.2649999999999997 1.0 1"/>
         <freejoint/>
        </body>
    <body pos="-6.01908215503697 -11.228866541592403 1.0" euler="0 0 2851.8070677395017" >
         <geom type="box" size="0.1 0.30000000000000004  1.0" rgba="0.0 0.25 1.0 1"/>
         <freejoint/>
        </body>
    <body pos="-4.751994216290321 -11.847528756208513 1.0" euler="0 0 2858.1444854202205" >
         <geom type="box" size="0.1 0.30000000000000004  1.0" rgba="0.0 0.23499999999999943 1.0 1"/>
         <freejoint/>
        </body>
    <body pos="-3.423992820219618 -12.322760985030543 1.0" euler="0 0 2864.4715567813414" >
         <geom type="box" size="0.1 0.30000000000000004  1.0" rgba="0.0 0.21999999999999975 1.0 1"/>
         <freejoint/>
        </body>
    <body pos="-2.0519556081154264 -12.648807037366488 1.0" euler="0 0 2870.7854526621754" >
         <geom type="box" size="0.1 0.30000000000000004  1.0" rgba="0.0 0.20499999999999963 1.0 1"/>
         <freejoint/>
        </body>
    <body pos="-0.6527998987898035 -12.822058672545555 1.0" euler="0 0 2877.0854592420264" >
         <geom type="box" size="0.1 0.30000000000000004  1.0" rgba="0.0 0.18999999999999995 1.0 1"/>
         <freejoint/>
        </body>
    <body pos="0.7573461796486682 -12.840811845213704 1.0" euler="0 0 2883.3753729702844" >
         <geom type="box" size="0.1 0.30000000000000004  1.0" rgba="0.0 0.17499999999999982 1.0 1"/>
         <freejoint/>
        </body>
    <body pos="2.1614979523064144 -12.704992226317012 1.0" euler="0 0 2889.6552739879944" >
         <geom type="box" size="0.1 0.30000000000000004  1.0" rgba="0.0 0.16000000000000014 1.0 1"/>
         <freejoint/>
        </body>
    <body pos="3.5414610508386066 -12.41673890779914 1.0" euler="0 0 2895.919033495184" >
         <geom type="box" size="0.1 0.30000000000000004  1.0" rgba="0.0 0.14500000000000046 1.0 1"/>
         <freejoint/>
        </body>
    <body pos="4.8820774359318575 -11.97961892611218 1.0" euler="0 0 2902.1724654198483" >
         <geom type="box" size="0.1 0.30000000000000004  1.0" rgba="0.0 0.1299999999999999 1.0 1"/>
         <freejoint/>
        </body>
    <body pos="6.167540159470251 -11.398955850744647 1.0" euler="0 0 2908.4161294512146" >
         <geom type="box" size="0.1 0.30000000000000004  1.0" rgba="0.0 0.11500000000000021 1.0 1"/>
         <freejoint/>
        </body>
    <body pos="7.3820495669879165 -10.682170385631823 1.0" euler="0 0 2914.6469046661" >
         <geom type="box" size="0.1 0.30000000000000004  1.0" rgba="0.0 0.09999999999999964 1.0 1"/>
         <freejoint/>
        </body>
    <body pos="8.511377953711834 -9.838108630260635 1.0" euler="0 0 2920.86451551618" >
         <geom type="box" size="0.1 0.30000000000000004  1.0" rgba="0.0 0.08499999999999996 1.0 1"/>
         <freejoint/>
        </body>
    <body pos="9.54303140043505 -8.876441137806742 1.0" euler="0 0 2927.072597265432" >
         <geom type="box" size="0.1 0.30000000000000004  1.0" rgba="0.0 0.06999999999999984 1.0 1"/>
         <freejoint/>
        </body>
    <body pos="10.464928816352183 -7.808635966790617 1.0" euler="0 0 2933.27073370235" >
         <geom type="box" size="0.1 0.30000000000000004  1.0" rgba="0.0 0.05500000000000016 1.0 1"/>
         <freejoint/>
        </body>
    <body pos="11.26571890655644 -6.648424481539229 1.0" euler="0 0 2939.4531695148635" >
         <geom type="box" size="0.1 0.30000000000000004  1.0" rgba="0.0 0.040000000000000036 1.0 1"/>
         <freejoint/>
        </body>
    <body pos="11.937188405864184 -5.40834095313806 1.0" euler="0 0 2945.6263091649284" >
         <geom type="box" size="0.1 0.30000000000000004  1.0" rgba="0.0 0.025000000000000355 1.0 1"/>
         <freejoint/>
        </body>
    <body pos="12.471658280987233 -4.102830451222488 1.0" euler="0 0 2951.790225125804" >
         <geom type="box" size="0.1 0.30000000000000004  1.0" rgba="0.0 0.009999999999999787 1.0 1"/>
         <freejoint/>
        </body>
    <body pos="12.86280444213234 -2.7481458348554177 1.0" euler="0 0 2957.9400394535496" >
         <geom type="box" size="0.1 0.30000000000000004  1.0" rgba="0.004999999999999893 0.0 1.0 1"/>
         <freejoint/>
        </body>
    <body pos="13.106671941138725 -1.3593297836583966 1.0" euler="0 0 2964.0788630557317" >
         <geom type="box" size="0.1 0.30000000000000004  1.0" rgba="0.020000000000000462 0.0 1.0 1"/>
         <freejoint/>
        </body>
    <body pos="13.200724001850853 0.04808113211817638 1.0" euler="0 0 2970.208688081197" >
         <geom type="box" size="0.1 0.30000000000000004  1.0" rgba="0.03500000000000014 0.0 1.0 1"/>
         <freejoint/>
        </body>
    <body pos="13.144062087347347 1.4573190480253482 1.0" euler="0 0 2976.3267040362894" >
         <geom type="box" size="0.1 0.30000000000000004  1.0" rgba="0.05000000000000071 0.0 1.0 1"/>
         <freejoint/>
        </body>
    <body pos="12.93771011765804 2.8520743616765016 1.0" euler="0 0 2982.4318238876194" >
         <geom type="box" size="0.1 0.30000000000000004  1.0" rgba="0.0649999999999995 0.0 1.0 1"/>
         <freejoint/>
        </body>
    <body pos="12.584131080856158 4.217470999964064 1.0" euler="0 0 2988.528164810075" >
         <geom type="box" size="0.1 0.30000000000000004  1.0" rgba="0.08000000000000007 0.0 1.0 1"/>
         <freejoint/>
        </body>
    <body pos="12.087530908156541 5.537857869073581 1.0" euler="0 0 2994.6147094905778" >
         <geom type="box" size="0.1 0.30000000000000004  1.0" rgba="0.09499999999999975 0.0 1.0 1"/>
         <freejoint/>
        </body>
    <body pos="11.454237683172044 6.797439532261371 1.0" euler="0 0 3000.6867244992904" >
         <geom type="box" size="0.1 0.30000000000000004  1.0" rgba="0.11000000000000032 0.0 1.0 1"/>
         <freejoint/>
        </body>
    <body pos="10.691039024556911 7.983428330069357 1.0" euler="0 0 3006.7501749147136" >
         <geom type="box" size="0.1 0.30000000000000004  1.0" rgba="0.125 0.0 1.0 1"/>
         <freejoint/>
        </body>
    <body pos="9.806561507327588 9.082605431693242 1.0" euler="0 0 3012.8051263147054" >
         <geom type="box" size="0.1 0.30000000000000004  1.0" rgba="0.14000000000000057 0.0 1.0 1"/>
         <freejoint/>
        </body>
    <body pos="8.811893796974783 10.081734474833492 1.0" euler="0 0 3018.845066437671" >
         <geom type="box" size="0.1 0.30000000000000004  1.0" rgba="0.15500000000000025 0.0 1.0 1"/>
         <freejoint/>
        </body>
    <body pos="7.717336272544485 10.970971737414326 1.0" euler="0 0 3024.8762070547473" >
         <geom type="box" size="0.1 0.30000000000000004  1.0" rgba="0.16999999999999993 0.0 1.0 1"/>
         <freejoint/>
        </body>
    <body pos="6.534999123852705 11.740620844421562 1.0" euler="0 0 3030.899055900934" >
         <geom type="box" size="0.1 0.30000000000000004  1.0" rgba="0.1850000000000005 0.0 1.0 1"/>
         <freejoint/>
        </body>
    <body pos="5.279137596776905 12.38174721236397 1.0" euler="0 0 3036.908320752259" >
         <geom type="box" size="0.1 0.30000000000000004  1.0" rgba="0.20000000000000018 0.0 1.0 1"/>
         <freejoint/>
        </body>
    <body pos="3.962965127929786 12.88799787502832 1.0" euler="0 0 3042.907719730663" >
         <geom type="box" size="0.1 0.30000000000000004  1.0" rgba="0.21499999999999986 0.0 1.0 1"/>
         <freejoint/>
        </body>
    <body pos="2.6005859572793586 13.25410869842158 1.0" euler="0 0 3048.899029218188" >
         <geom type="box" size="0.1 0.30000000000000004  1.0" rgba="0.22999999999999954 0.0 1.0 1"/>
         <freejoint/>
        </body>
    <body pos="1.207938298705145 13.476051812139474 1.0" euler="0 0 3054.8779287653992" >
         <geom type="box" size="0.1 0.30000000000000004  1.0" rgba="0.2450000000000001 0.0 1.0 1"/>
         <freejoint/>
        </body>
    <body pos="-0.2001472398027078 13.551812641855436 1.0" euler="0 0 3060.846142043612" >
         <geom type="box" size="0.1 0.30000000000000004  1.0" rgba="0.2599999999999998 0.0 1.0 1"/>
         <freejoint/>
        </body>
    <body pos="-1.609028591538085 13.480784592629476 1.0" euler="0 0 3066.806463282712" >
         <geom type="box" size="0.1 0.30000000000000004  1.0" rgba="0.27500000000000036 0.0 1.0 1"/>
         <freejoint/>
        </body>
    <body pos="-3.0026253275105597 13.263991438724423 1.0" euler="0 0 3072.7553028193306" >
         <geom type="box" size="0.1 0.30000000000000004  1.0" rgba="0.29000000000000004 0.0 1.0 1"/>
         <freejoint/>
        </body>
    <body pos="-4.366008047632912 12.904099328763728 1.0" euler="0 0 3078.6928744323727" >
         <geom type="box" size="0.1 0.30000000000000004  1.0" rgba="0.3049999999999997 0.0 1.0 1"/>
         <freejoint/>
        </body>
    <body pos="-5.685391043901495 12.404957139980535 1.0" euler="0 0 3084.6227467617887" >
         <geom type="box" size="0.1 0.30000000000000004  1.0" rgba="0.3200000000000003 0.0 1.0 1"/>
         <freejoint/>
        </body>
    <body pos="-6.9460229490516765 11.77234647860559 1.0" euler="0 0 3090.5418270008217" >
         <geom type="box" size="0.1 0.30000000000000004  1.0" rgba="0.33499999999999996 0.0 1.0 1"/>
         <freejoint/>
        </body>
    <body pos="-8.134418827802621 11.013408769421293 1.0" euler="0 0 3096.4492893882516" >
         <geom type="box" size="0.1 0.30000000000000004  1.0" rgba="0.34999999999999964 0.0 1.0 1"/>
         <freejoint/>
        </body>
    <body pos="-9.238873296763819 10.135876030920198 1.0" euler="0 0 3102.349240679075" >
         <geom type="box" size="0.1 0.30000000000000004  1.0" rgba="0.3650000000000002 0.0 1.0 1"/>
         <freejoint/>
        </body>
    <body pos="-10.247255376437003 9.149605946325634 1.0" euler="0 0 3108.2388578441783" >
         <geom type="box" size="0.1 0.30000000000000004  1.0" rgba="0.3799999999999999 0.0 1.0 1"/>
         <freejoint/>
        </body>
    <body pos="-11.148896548141552 8.065494336919116 1.0" euler="0 0 3114.1167321487014" >
         <geom type="box" size="0.1 0.30000000000000004  1.0" rgba="0.39500000000000046 0.0 1.0 1"/>
         <freejoint/>
        </body>
    <body pos="-11.935143585467806 6.894291961237719 1.0" euler="0 0 3119.987279098971" >
         <geom type="box" size="0.1 0.30000000000000004  1.0" rgba="0.41000000000000014 0.0 1.0 1"/>
         <freejoint/>
        </body>
    <body pos="-12.597507964367624 5.648936696864021 1.0" euler="0 0 3125.847725013359" >
         <geom type="box" size="0.1 0.30000000000000004  1.0" rgba="0.4250000000000007 0.0 1.0 1"/>
         <freejoint/>
        </body>
    <body pos="-13.129170197699318 4.3429422202132875 1.0" euler="0 0 3131.696521370384" >
         <geom type="box" size="0.1 0.30000000000000004  1.0" rgba="0.4399999999999995 0.0 1.0 1"/>
         <freejoint/>
        </body>
    <body pos="-13.525194831238762 2.9890117258573357 1.0" euler="0 0 3137.5381697907746" >
         <geom type="box" size="0.1 0.30000000000000004  1.0" rgba="0.45500000000000007 0.0 1.0 1"/>
         <freejoint/>
        </body>
    <body pos="-13.781423598631928 1.601943439937232 1.0" euler="0 0 3143.369731963939" >
         <geom type="box" size="0.1 0.30000000000000004  1.0" rgba="0.46999999999999975 0.0 1.0 1"/>
         <freejoint/>
        </body>
    <body pos="-13.895460946995517 0.19646772042913424 1.0" euler="0 0 3149.1899497823842" >
         <geom type="box" size="0.1 0.30000000000000004  1.0" rgba="0.4850000000000003 0.0 1.0 1"/>
         <freejoint/>
        </body>
    <body pos="-13.86642146449011 -1.2139338102772272 1.0" euler="0 0 3155.003194873291" >
         <geom type="box" size="0.1 0.30000000000000004  1.0" rgba="0.5 0.0 1.0 1"/>
         <freejoint/>
        </body>
    <body pos="-13.694791571351356 -2.6139463315602605 1.0" euler="0 0 3160.806156585592" >
         <geom type="box" size="0.1 0.30000000000000004  1.0" rgba="0.5150000000000006 0.0 1.0 1"/>
         <freejoint/>
        </body>
    <body pos="-13.382661861202019 -3.9891085572837603 1.0" euler="0 0 3166.598284820266" >
         <geom type="box" size="0.1 0.30000000000000004  1.0" rgba="0.5300000000000002 0.0 1.0 1"/>
         <freejoint/>
        </body>
    <body pos="-12.933193223154493 -5.326350289086982 1.0" euler="0 0 3172.3836114405776" >
         <geom type="box" size="0.1 0.30000000000000004  1.0" rgba="0.5449999999999999 0.0 1.0 1"/>
         <freejoint/>
        </body>
    <body pos="-12.351444998968212 -6.611203939055621 1.0" euler="0 0 3178.158251825777" >
         <geom type="box" size="0.1 0.30000000000000004  1.0" rgba="0.5600000000000005 0.0 1.0 1"/>
         <freejoint/>
        </body>
    <body pos="-11.643556492360572 -7.830863545382951 1.0" euler="0 0 3183.9227692416043" >
         <geom type="box" size="0.1 0.30000000000000004  1.0" rgba="0.5750000000000002 0.0 1.0 1"/>
         <freejoint/>
        </body>
    <body pos="-10.816413583235295 -8.973791244162555 1.0" euler="0 0 3189.6806521694666" >
         <geom type="box" size="0.1 0.30000000000000004  1.0" rgba="0.5899999999999999 0.0 1.0 1"/>
         <freejoint/>
        </body>
    <body pos="-9.879203451185871 -10.027648704062235 1.0" euler="0 0 3195.42724629525" >
         <geom type="box" size="0.1 0.30000000000000004  1.0" rgba="0.6050000000000004 0.0 1.0 1"/>
         <freejoint/>
        </body>
    <body pos="-8.841253513689063 -10.982408245736243 1.0" euler="0 0 3201.1646217236334" >
         <geom type="box" size="0.1 0.30000000000000004  1.0" rgba="0.6200000000000001 0.0 1.0 1"/>
         <freejoint/>
        </body>
    <body pos="-7.712571709848417 -11.829041901138043 1.0" euler="0 0 3206.8955259094664" >
         <geom type="box" size="0.1 0.30000000000000004  1.0" rgba="0.6349999999999998 0.0 1.0 1"/>
         <freejoint/>
        </body>
    <body pos="-6.505691770854592 -12.558446294766007 1.0" euler="0 0 3212.614344856026" >
         <geom type="box" size="0.1 0.30000000000000004  1.0" rgba="0.6500000000000004 0.0 1.0 1"/>
         <freejoint/>
        </body>
    <body pos="-5.231972745366613 -13.164108701399558 1.0" euler="0 0 3218.32503744362" >
         <geom type="box" size="0.1 0.30000000000000004  1.0" rgba="0.665 0.0 1.0 1"/>
         <freejoint/>
        </body>
    <body pos="-3.9037100594820027 -13.64028344069668 1.0" euler="0 0 3224.0294182556513" >
         <geom type="box" size="0.1 0.30000000000000004  1.0" rgba="0.6799999999999997 0.0 1.0 1"/>
         <freejoint/>
        </body>
    <body pos="-2.5357255566601298 -13.981949365143853 1.0" euler="0 0 3229.7207291923824" >
         <geom type="box" size="0.1 0.30000000000000004  1.0" rgba="0.6950000000000003 0.0 1.0 1"/>
         <freejoint/>
        </body>
    <body pos="-1.1401169210561959 -14.186391170356226 1.0" euler="0 0 3235.4051886425227" >
         <geom type="box" size="0.1 0.30000000000000004  1.0" rgba="0.71 0.0 1.0 1"/>
         <freejoint/>
        </body>
    <body pos="0.2693771900889608 -14.251665479329429 1.0" euler="0 0 3241.0828445612538" >
         <geom type="box" size="0.1 0.30000000000000004  1.0" rgba="0.7249999999999996 0.0 1.0 1"/>
         <freejoint/>
        </body>
    <body pos="1.6773879941360872 -14.177355623201493 1.0" euler="0 0 3246.7475583654596" >
         <geom type="box" size="0.1 0.30000000000000004  1.0" rgba="0.7400000000000002 0.0 1.0 1"/>
         <freejoint/>
        </body>
    <body pos="3.0718558685584476 -13.964367244199877 1.0" euler="0 0 3252.4062251725118" >
         <geom type="box" size="0.1 0.30000000000000004  1.0" rgba="0.7549999999999999 0.0 1.0 1"/>
         <freejoint/>
        </body>
    <body pos="4.438682971451346 -13.61494825817547 1.0" euler="0 0 3258.0567666660168" >
         <geom type="box" size="0.1 0.30000000000000004  1.0" rgba="0.7700000000000005 0.0 1.0 1"/>
         <freejoint/>
        </body>
    <body pos="5.763871838261229 -13.132976681135972 1.0" euler="0 0 3263.695969352025" >
         <geom type="box" size="0.1 0.30000000000000004  1.0" rgba="0.7850000000000001 0.0 1.0 1"/>
         <freejoint/>
        </body>
    <body pos="7.035917483053183 -12.522860527103683 1.0" euler="0 0 3269.329275028885" >
         <geom type="box" size="0.1 0.30000000000000004  1.0" rgba="0.8000000000000007 0.0 1.0 1"/>
         <freejoint/>
        </body>
    <body pos="8.241751685681946 -11.79103297709049 1.0" euler="0 0 3274.952959813174" >
         <geom type="box" size="0.1 0.30000000000000004  1.0" rgba="0.8149999999999995 0.0 1.0 1"/>
         <freejoint/>
        </body>
    <body pos="9.369911915045787 -10.944785225064633 1.0" euler="0 0 3280.5670775679064" >
         <geom type="box" size="0.1 0.30000000000000004  1.0" rgba="0.8300000000000001 0.0 1.0 1"/>
         <freejoint/>
        </body>
    <body pos="10.410409377042523 -9.991791675262066 1.0" euler="0 0 3286.1754448668835" >
         <geom type="box" size="0.1 0.30000000000000004  1.0" rgba="0.8449999999999998 0.0 1.0 1"/>
         <freejoint/>
        </body>
    <body pos="11.352396808985807 -8.94227293618253 1.0" euler="0 0 3291.7725270014816" >
         <geom type="box" size="0.1 0.30000000000000004  1.0" rgba="0.8600000000000003 0.0 1.0 1"/>
         <freejoint/>
        </body>
    <body pos="12.187698809952543 -7.8057593509943 1.0" euler="0 0 3297.3619773766154" >
         <geom type="box" size="0.1 0.30000000000000004  1.0" rgba="0.875 0.0 1.0 1"/>
         <freejoint/>
        </body>
    <body pos="12.908723474234566 -6.592706210195522 1.0" euler="0 0 3302.9458205039214" >
         <geom type="box" size="0.1 0.30000000000000004  1.0" rgba="0.8900000000000006 0.0 1.0 1"/>
         <freejoint/>
        </body>
    <body pos="13.50789938817804 -5.316396254072048 1.0" euler="0 0 3308.516550460706" >
         <geom type="box" size="0.1 0.30000000000000004  1.0" rgba="0.9050000000000002 0.0 1.0 1"/>
         <freejoint/>
        </body>
    <body pos="13.98061731221291 -3.9873004842472857 1.0" euler="0 0 3314.0817425836394" >
         <geom type="box" size="0.1 0.30000000000000004  1.0" rgba="0.9199999999999999 0.0 1.0 1"/>
         <freejoint/>
        </body>
    <body pos="14.32231764029521 -2.618460595416957 1.0" euler="0 0 3319.639389275758" >
         <geom type="box" size="0.1 0.30000000000000004  1.0" rgba="0.9350000000000005 0.0 1.0 1"/>
         <freejoint/>
        </body>
    <body pos="14.529844048600301 -1.2236569814661526 1.0" euler="0 0 3325.186092138122" >
         <geom type="box" size="0.1 0.30000000000000004  1.0" rgba="0.9500000000000002 0.0 1.0 1"/>
         <freejoint/>
        </body>
    <body pos="14.601651995804827 0.1853924584673498 1.0" euler="0 0 3330.7274269168747" >
         <geom type="box" size="0.1 0.30000000000000004  1.0" rgba="0.9649999999999999 0.0 1.0 1"/>
         <freejoint/>
        </body>
    <body pos="14.537165984803702 1.5944127808476416 1.0" euler="0 0 3336.259090558782" >
         <geom type="box" size="0.1 0.30000000000000004  1.0" rgba="0.9800000000000004 0.0 1.0 1"/>
         <freejoint/>
        </body>
    <body pos="14.33724529986797 2.9905568471418547 1.0" euler="0 0 3341.782194171402" >
         <geom type="box" size="0.1 0.30000000000000004  1.0" rgba="0.9950000000000001 0.0 1.0 1"/>
         <freejoint/>
        </body>
    <body pos="14.00373718747165 4.361695719794886 1.0" euler="0 0 3347.3000644936465" >
         <geom type="box" size="0.1 0.30000000000000004  1.0" rgba="1.0 0.0 0.9900000000000002 1"/>
         <freejoint/>
        </body>
    <body pos="13.540367163751544 5.693511173947262 1.0" euler="0 0 3352.8059868787977" >
         <geom type="box" size="0.1 0.30000000000000004  1.0" rgba="1.0 0.0 0.9749999999999996 1"/>
         <freejoint/>
        </body>
    <body pos="12.951175231604587 6.975203741371403 1.0" euler="0 0 3358.305879348335" >
         <geom type="box" size="0.1 0.30000000000000004  1.0" rgba="1.0 0.0 0.96 1"/>
         <freejoint/>
        </body>
    <body pos="12.241738442876425 8.194826606631231 1.0" euler="0 0 3363.7990207254916" >
         <geom type="box" size="0.1 0.30000000000000004  1.0" rgba="1.0 0.0 0.9450000000000003 1"/>
         <freejoint/>
        </body>
    <body pos="11.419362086013637 9.34034748188973 1.0" euler="0 0 3369.281089837491" >
         <geom type="box" size="0.1 0.30000000000000004  1.0" rgba="1.0 0.0 0.9299999999999997 1"/>
         <freejoint/>
        </body>
    <body pos="10.490841086373754 10.40264806516874 1.0" euler="0 0 3374.7581515538113" >
         <geom type="box" size="0.1 0.30000000000000004  1.0" rgba="1.0 0.0 0.915 1"/>
         <freejoint/>
        </body>
    <body pos="9.465488828630619 11.371284148938683 1.0" euler="0 0 3380.2259080854496" >
         <geom type="box" size="0.1 0.30000000000000004  1.0" rgba="1.0 0.0 0.9000000000000004 1"/>
         <freejoint/>
        </body>
    <body pos="8.352634616758982 12.237801125766358 1.0" euler="0 0 3385.685392383452" >
         <geom type="box" size="0.1 0.30000000000000004  1.0" rgba="1.0 0.0 0.8849999999999998 1"/>
         <freejoint/>
        </body>
    <body pos="7.161761656045176 12.994940907846493 1.0" euler="0 0 3391.1399962044634" >
         <geom type="box" size="0.1 0.30000000000000004  1.0" rgba="1.0 0.0 0.8700000000000001 1"/>
         <freejoint/>
        </body>
    <body pos="5.905334368825458 13.635061284826168 1.0" euler="0 0 3396.5826014019085" >
         <geom type="box" size="0.1 0.30000000000000004  1.0" rgba="1.0 0.0 0.8549999999999995 1"/>
         <freejoint/>
        </body>
    <body pos="4.593288866359552 14.15338817843751 1.0" euler="0 0 3402.0198692400927" >
         <geom type="box" size="0.1 0.30000000000000004  1.0" rgba="1.0 0.0 0.8399999999999999 1"/>
         <freejoint/>
        </body>
    <body pos="3.2379067587388133 14.545155688164497 1.0" euler="0 0 3407.4499853327166" >
         <geom type="box" size="0.1 0.30000000000000004  1.0" rgba="1.0 0.0 0.8249999999999993 1"/>
         <freejoint/>
        </body>
    <body pos="1.8521512755584553 14.806881894980611 1.0" euler="0 0 3412.8700648390072" >
         <geom type="box" size="0.1 0.30000000000000004  1.0" rgba="1.0 0.0 0.8100000000000005 1"/>
         <freejoint/>
        </body>
    <body pos="0.44709853018979906 14.936642409660498 1.0" euler="0 0 3418.2854773218414" >
         <geom type="box" size="0.1 0.30000000000000004  1.0" rgba="1.0 0.0 0.7949999999999999 1"/>
         <freejoint/>
        </body>
    <body pos="-0.9632828527850852 14.933316731092653 1.0" euler="0 0 3423.6907863525457" >
         <geom type="box" size="0.1 0.30000000000000004  1.0" rgba="1.0 0.0 0.7800000000000002 1"/>
         <freejoint/>
        </body>
    <body pos="-2.367275984942744 14.797183212847028 1.0" euler="0 0 3429.0892449849443" >
         <geom type="box" size="0.1 0.30000000000000004  1.0" rgba="1.0 0.0 0.7649999999999997 1"/>
         <freejoint/>
        </body>
    <body pos="-3.7527776813035527 14.529497366752592 1.0" euler="0 0 3434.4822352786264" >
         <geom type="box" size="0.1 0.30000000000000004  1.0" rgba="1.0 0.0 0.75 1"/>
         <freejoint/>
        </body>
    <body pos="-5.106060264481218 14.133164689919631 1.0" euler="0 0 3439.8638837109006" >
         <geom type="box" size="0.1 0.30000000000000004  1.0" rgba="1.0 0.0 0.7349999999999994 1"/>
         <freejoint/>
        </body>
    <body pos="-6.416953463262947 13.611385647868511 1.0" euler="0 0 3445.2410712506176" >
         <geom type="box" size="0.1 0.30000000000000004  1.0" rgba="1.0 0.0 0.7199999999999998 1"/>
         <freejoint/>
        </body>
    <body pos="-7.672935340375403 12.969269387560239 1.0" euler="0 0 3450.6095917348557" >
         <geom type="box" size="0.1 0.30000000000000004  1.0" rgba="1.0 0.0 0.7050000000000001 1"/>
         <freejoint/>
        </body>
    <body pos="-8.863259994434356 12.212584672683867 1.0" euler="0 0 3455.970196844479" >
         <geom type="box" size="0.1 0.30000000000000004  1.0" rgba="1.0 0.0 0.6899999999999995 1"/>
         <freejoint/>
        </body>
    <body pos="-9.978337214283918 11.347531181881555 1.0" euler="0 0 3461.3264562574627" >
         <geom type="box" size="0.1 0.30000000000000004  1.0" rgba="1.0 0.0 0.6749999999999998 1"/>
         <freejoint/>
        </body>
    <body pos="-11.006988287011271 10.383083291834732 1.0" euler="0 0 3466.6707279612174" >
         <geom type="box" size="0.1 0.30000000000000004  1.0" rgba="1.0 0.0 0.6600000000000001 1"/>
         <freejoint/>
        </body>
    <body pos="-11.941876926164532 9.32644982524734 1.0" euler="0 0 3472.010628618097" >
         <geom type="box" size="0.1 0.30000000000000004  1.0" rgba="1.0 0.0 0.6449999999999996 1"/>
         <freejoint/>
        </body>
    <body pos="-12.774371021585157 8.187513303215345 1.0" euler="0 0 3477.3428578838216" >
         <geom type="box" size="0.1 0.30000000000000004  1.0" rgba="1.0 0.0 0.6299999999999999 1"/>
         <freejoint/>
        </body>
    <body pos="-13.497314282519632 6.976469314323153 1.0" euler="0 0 3482.6665371861054" >
         <geom type="box" size="0.1 0.30000000000000004  1.0" rgba="1.0 0.0 0.6150000000000002 1"/>
         <freejoint/>
        </body>
    <body pos="-14.105150491050177 5.7028414383575186 1.0" euler="0 0 3487.9860656963433" >
         <geom type="box" size="0.1 0.30000000000000004  1.0" rgba="1.0 0.0 0.5999999999999996 1"/>
         <freejoint/>
        </body>
    <body pos="-14.592027866420375 4.379380510512097 1.0" euler="0 0 3493.2943721524452" >
         <geom type="box" size="0.1 0.30000000000000004  1.0" rgba="1.0 0.0 0.585 1"/>
         <freejoint/>
        </body>
    <body pos="-14.954571558147146 3.0159418732729977 1.0" euler="0 0 3498.5978966464386" >
         <geom type="box" size="0.1 0.30000000000000004  1.0" rgba="1.0 0.0 0.5700000000000003 1"/>
         <freejoint/>
        </body>
    <body pos="-15.189599738676419 1.6248224178076294 1.0" euler="0 0 3503.8943220056244" >
         <geom type="box" size="0.1 0.30000000000000004  1.0" rgba="1.0 0.0 0.5549999999999997 1"/>
         <freejoint/>
        </body>
    <body pos="-15.29525978129901 0.2183884469552982 1.0" euler="0 0 3509.1819762279874" >
         <geom type="box" size="0.1 0.30000000000000004  1.0" rgba="1.0 0.0 0.54 1"/>
         <freejoint/>
        </body>
    <body pos="-15.27086553559005 -1.192636522207848 1.0" euler="0 0 3514.465667943903" >
         <geom type="box" size="0.1 0.30000000000000004  1.0" rgba="1.0 0.0 0.5250000000000004 1"/>
         <freejoint/>
        </body>
    <body pos="-15.116854084390157 -2.594424247275078 1.0" euler="0 0 3519.738489935972" >
         <geom type="box" size="0.1 0.30000000000000004  1.0" rgba="1.0 0.0 0.5099999999999998 1"/>
         <freejoint/>
        </body>
    <body pos="-14.834582699201494 -3.976724540086946 1.0" euler="0 0 3525.006522600244" >
         <geom type="box" size="0.1 0.30000000000000004  1.0" rgba="1.0 0.0 0.4950000000000001 1"/>
         <freejoint/>
        </body>
    <body pos="-14.42663654092503 -5.327308649664454 1.0" euler="0 0 3530.2676216160253" >
         <geom type="box" size="0.1 0.30000000000000004  1.0" rgba="1.0 0.0 0.47999999999999954 1"/>
         <freejoint/>
        </body>
    <body pos="-13.89680234649643 -6.634427558276501 1.0" euler="0 0 3535.5201254372178" >
         <geom type="box" size="0.1 0.30000000000000004  1.0" rgba="1.0 0.0 0.46499999999999986 1"/>
         <freejoint/>
        </body>
    <body pos="-13.24915745949526 -7.888322845491652 1.0" euler="0 0 3540.768848665681" >
         <geom type="box" size="0.1 0.30000000000000004  1.0" rgba="1.0 0.0 0.4499999999999993 1"/>
         <freejoint/>
        </body>
    <body pos="-12.490188748725902 -9.07687085409054 1.0" euler="0 0 3546.0066574016514" >
         <geom type="box" size="0.1 0.30000000000000004  1.0" rgba="1.0 0.0 0.4350000000000005 1"/>
         <freejoint/>
        </body>
    <body pos="-11.625496427990639 -10.19171824081519 1.0" euler="0 0 3551.240057097153" >
         <geom type="box" size="0.1 0.30000000000000004  1.0" rgba="1.0 0.0 0.41999999999999993 1"/>
         <freejoint/>
        </body>
    <body pos="-10.662815628156348 -11.22303460002319 1.0" euler="0 0 3556.466297842116" >
         <geom type="box" size="0.1 0.30000000000000004  1.0" rgba="1.0 0.0 0.40500000000000025 1"/>
         <freejoint/>
        </body>
    <body pos="-9.610482226169436 -12.16221550860727 1.0" euler="0 0 3561.6845007932507" >
         <geom type="box" size="0.1 0.30000000000000004  1.0" rgba="1.0 0.0 0.3899999999999997 1"/>
         <freejoint/>
        </body>
    <body pos="-8.476402802203125 -13.002328661115037 1.0" euler="0 0 3566.8990989301324" >
         <geom type="box" size="0.1 0.30000000000000004  1.0" rgba="1.0 0.0 0.375 1"/>
         <freejoint/>
        </body>
    <body pos="-7.271770634580032 -13.73535070222586 1.0" euler="0 0 3572.102356294839" >
         <geom type="box" size="0.1 0.30000000000000004  1.0" rgba="1.0 0.0 0.35999999999999943 1"/>
         <freejoint/>
        </body>
    <body pos="-6.004875141587981 -14.356493651206423 1.0" euler="0 0 3577.3019572877315" >
         <geom type="box" size="0.1 0.30000000000000004  1.0" rgba="1.0 0.0 0.34499999999999975 1"/>
         <freejoint/>
        </body>
    <body pos="-4.68718223429282 -14.860234311963033 1.0" euler="0 0 3582.4937985937017" >
         <geom type="box" size="0.1 0.30000000000000004  1.0" rgba="1.0 0.0 0.33000000000000007 1"/>
         <freejoint/>
        </body>
    <body pos="-3.3294308976427156 -15.242699521934828 1.0" euler="0 0 3587.6785259227736" >
         <geom type="box" size="0.1 0.30000000000000004  1.0" rgba="1.0 0.0 0.3149999999999995 1"/>
         <freejoint/>
        </body>
    <body pos="-1.942023134987479 -15.501051548127665 1.0" euler="0 0 3592.8590011494944" >
         <geom type="box" size="0.1 0.30000000000000004  1.0" rgba="1.0 0.0 0.2999999999999998 1"/>
         <freejoint/>
        </body>
    <body pos="-0.5380033182316891 -15.633080115465793 1.0" euler="0 0 3598.0289771069774" >
         <geom type="box" size="0.1 0.30000000000000004  1.0" rgba="1.0 0.0 0.28500000000000014 1"/>
         <freejoint/>
        </body>
    <body pos="0.8730965944393808 -15.638073125537302 1.0" euler="0 0 3603.1955899106483" >
         <geom type="box" size="0.1 0.30000000000000004  1.0" rgba="1.0 0.0 0.2699999999999996 1"/>
         <freejoint/>
        </body>
    <body pos="2.278348257340638 -15.516104178816759 1.0" euler="0 0 3608.3534816103243" >
         <geom type="box" size="0.1 0.30000000000000004  1.0" rgba="1.0 0.0 0.2549999999999999 1"/>
         <freejoint/>
        </body>
    <body pos="3.6671558768694004 -15.268305407984762 1.0" euler="0 0 3613.5055351118986" >
         <geom type="box" size="0.1 0.30000000000000004  1.0" rgba="1.0 0.0 0.2400000000000002 1"/>
         <freejoint/>
        </body>
    <body pos="5.0284255509355225 -14.896747507348786 1.0" euler="0 0 3618.6522087173785" >
         <geom type="box" size="0.1 0.30000000000000004  1.0" rgba="1.0 0.0 0.22499999999999964 1"/>
         <freejoint/>
        </body>
    <body pos="6.350259505923274 -14.404895467119491 1.0" euler="0 0 3623.7898220454917" >
         <geom type="box" size="0.1 0.30000000000000004  1.0" rgba="1.0 0.0 0.20999999999999996 1"/>
         <freejoint/>
        </body>
    <body pos="7.623566465098741 -13.796271556977334 1.0" euler="0 0 3628.9242342287976" >
         <geom type="box" size="0.1 0.30000000000000004  1.0" rgba="1.0 0.0 0.19500000000000028 1"/>
         <freejoint/>
        </body>
    <body pos="8.836511606850054 -13.076718577071667 1.0" euler="0 0 3634.0486173895297" >
         <geom type="box" size="0.1 0.30000000000000004  1.0" rgba="1.0 0.0 0.17999999999999972 1"/>
         <freejoint/>
        </body>
    <body pos="9.980856200268512 -12.251364099253772 1.0" euler="0 0 3639.168776201236" >
         <geom type="box" size="0.1 0.30000000000000004  1.0" rgba="1.0 0.0 0.16500000000000004 1"/>
         <freejoint/>
        </body>
    <body pos="11.04693103911052 -11.327293772590954 1.0" euler="0 0 3644.282086381683" >
         <geom type="box" size="0.1 0.30000000000000004  1.0" rgba="1.0 0.0 0.15000000000000036 1"/>
         <freejoint/>
        </body>
    <body pos="12.026285215071896 -10.312103717538191 1.0" euler="0 0 3649.388107888462" >
         <geom type="box" size="0.1 0.30000000000000004  1.0" rgba="1.0 0.0 0.1349999999999998 1"/>
         <freejoint/>
        </body>
    <body pos="12.911880046455764 -9.213221476957514 1.0" euler="0 0 3654.4903928347185" >
         <geom type="box" size="0.1 0.30000000000000004  1.0" rgba="1.0 0.0 0.1200000000000001 1"/>
         <freejoint/>
        </body>
    <body pos="13.695720903625556 -8.040890453830754 1.0" euler="0 0 3659.582392001787" >
         <geom type="box" size="0.1 0.30000000000000004  1.0" rgba="1.0 0.0 0.10499999999999954 1"/>
         <freejoint/>
        </body>
    <body pos="14.372876270924063 -6.802802956907631 1.0" euler="0 0 3664.6714133691153" >
         <geom type="box" size="0.1 0.30000000000000004  1.0" rgba="1.0 0.0 0.08999999999999986 1"/>
         <freejoint/>
        </body>
    <body pos="14.937357475593824 -5.510151980675951 1.0" euler="0 0 3669.751789855424" >
         <geom type="box" size="0.1 0.30000000000000004  1.0" rgba="1.0 0.0 0.07499999999999929 1"/>
         <freejoint/>
        </body>
    <body pos="15.385287507814963 -4.172314776037968 1.0" euler="0 0 3674.826968729241" >
         <geom type="box" size="0.1 0.30000000000000004  1.0" rgba="1.0 0.0 0.0600000000000005 1"/>
         <freejoint/>
        </body>
    <body pos="15.713195338104633 -2.7999476497429927 1.0" euler="0 0 3679.8964613814524" >
         <geom type="box" size="0.1 0.30000000000000004  1.0" rgba="1.0 0.0 0.04499999999999993 1"/>
         <freejoint/>
        </body>
    <body pos="15.918353749351468 -1.4064356018604485 1.0" euler="0 0 3684.9508524314274" >
         <geom type="box" size="0.1 0.30000000000000004  1.0" rgba="1.0 0.0 0.03000000000000025 1"/>
         <freejoint/>
        </body>
    <body pos="16.0 -3.9188697572715304e-14 1.0" euler="25 0 3690.0" >
         <geom type="box" size="0.1 0.30000000000000004  1.0" rgba="1.0 0.0 0.01499999999999968 1"/>
         <freejoint/>
        </body>
  </worldbody>
</mujoco>
